{
  "nodes" : [ {
    "name" : "student",
    "group" : 0.75
  }, {
    "name" : "model",
    "group" : 0.385
  }, {
    "name" : "datum",
    "group" : 0.369
  }, {
    "name" : "method",
    "group" : 0.193
  }, {
    "name" : "paper",
    "group" : 0.163
  }, {
    "name" : "system",
    "group" : 0.133
  }, {
    "name" : "result",
    "group" : 0.116
  }, {
    "name" : "approach",
    "group" : 0.108
  }, {
    "name" : "skill",
    "group" : 0.077
  }, {
    "name" : "analysis",
    "group" : 0.074
  }, {
    "name" : "student",
    "group" : 0.75
  }, {
    "name" : "model",
    "group" : 0.385
  }, {
    "name" : "datum",
    "group" : 0.369
  }, {
    "name" : "method",
    "group" : 0.193
  }, {
    "name" : "paper",
    "group" : 0.163
  }, {
    "name" : "system",
    "group" : 0.133
  }, {
    "name" : "result",
    "group" : 0.116
  }, {
    "name" : "approach",
    "group" : 0.108
  }, {
    "name" : "skill",
    "group" : 0.077
  }, {
    "name" : "analysis",
    "group" : 0.074
  }, {
    "name" : "current_student",
    "group" : 0.003
  }, {
    "name" : "cognitive_tutor_educational_software",
    "group" : 0.001
  }, {
    "name" : "entire_school_year",
    "group" : 0.003
  }, {
    "name" : "programming_exercise",
    "group" : 0.003
  }, {
    "name" : "national_programming_online_tutorial",
    "group" : 0.003
  }, {
    "name" : "academic_mentor_profile",
    "group" : 0.003
  }, {
    "name" : "university_life",
    "group" : 0.003
  }, {
    "name" : "administrative_system",
    "group" : 0.005
  }, {
    "name" : "further_career_goal",
    "group" : 0.017
  }, {
    "name" : "non",
    "group" : 0.0
  }, {
    "name" : "hands",
    "group" : 0.0
  }, {
    "name" : "logical_concept",
    "group" : 0.005
  }, {
    "name" : "decreasing_use_of_resource",
    "group" : 0.005
  }, {
    "name" : "new_concept",
    "group" : 0.005
  }, {
    "name" : "open_lab_consulting_hour",
    "group" : 0.003
  }, {
    "name" : "climate_change",
    "group" : 0.003
  }, {
    "name" : "population",
    "group" : 0.003
  }, {
    "name" : "basic_declarative_knowledge",
    "group" : 0.004
  }, {
    "name" : "interleaved_representation",
    "group" : 0.003
  }, {
    "name" : "acquisition_phase",
    "group" : 0.004
  }, {
    "name" : "learning_rate",
    "group" : 0.003
  }, {
    "name" : "srl",
    "group" : 0.0
  }, {
    "name" : "individual_hint_processing_proficiency",
    "group" : 0.003
  }, {
    "name" : "online_programming_environment",
    "group" : 0.003
  }, {
    "name" : "terms_of_skill_mastery",
    "group" : 0.001
  }, {
    "name" : "meta",
    "group" : 0.0
  }, {
    "name" : "ordering_of_use",
    "group" : 0.003
  }, {
    "name" : "series_of_activity",
    "group" : 0.005
  }, {
    "name" : "choice",
    "group" : 0.002
  }, {
    "name" : "computer_system",
    "group" : 0.007
  }, {
    "name" : "course_of_year",
    "group" : 0.008
  }, {
    "name" : "educational_system_help",
    "group" : 0.006
  }, {
    "name" : "dataset",
    "group" : 0.016
  }, {
    "name" : "problem",
    "group" : 0.046
  }, {
    "name" : "similarity_of_profile",
    "group" : 0.005
  }, {
    "name" : "university",
    "group" : 0.005
  }, {
    "name" : "learning_session",
    "group" : 0.005
  }, {
    "name" : "model_parameter",
    "group" : 0.01
  }, {
    "name" : "carelessness",
    "group" : 0.015
  }, {
    "name" : "question",
    "group" : 0.028
  }, {
    "name" : "computer",
    "group" : 0.028
  }, {
    "name" : "transfer_model",
    "group" : 0.009
  }, {
    "name" : "intelligent_tutoring_system",
    "group" : 0.074
  }, {
    "name" : "attempt",
    "group" : 0.006
  }, {
    "name" : "course",
    "group" : 0.039
  }, {
    "name" : "inquiry",
    "group" : 0.007
  }, {
    "name" : "online_course",
    "group" : 0.017
  }, {
    "name" : "tutoring_system",
    "group" : 0.045
  }, {
    "name" : "theory",
    "group" : 0.021
  }, {
    "name" : "test",
    "group" : 0.011
  }, {
    "name" : "error",
    "group" : 0.014
  }, {
    "name" : "solution",
    "group" : 0.013
  }, {
    "name" : "material",
    "group" : 0.02
  }, {
    "name" : "is a",
    "group" : 0.0
  }, {
    "name" : "feedback",
    "group" : 0.018
  }, {
    "name" : "task",
    "group" : 0.023
  }, {
    "name" : "time",
    "group" : 0.054
  }, {
    "name" : "process",
    "group" : 0.045
  }, {
    "name" : "knowledge",
    "group" : 0.047
  }, {
    "name" : "previous_student",
    "group" : 0.004
  }, {
    "name" : "college_student",
    "group" : 0.004
  }, {
    "name" : "individual_student",
    "group" : 0.005
  }, {
    "name" : "thousands_of_student",
    "group" : 0.005
  }, {
    "name" : "hundreds_of_student",
    "group" : 0.003
  }, {
    "name" : "account_student",
    "group" : 0.004
  }, {
    "name" : "middle_school_student",
    "group" : 0.002
  }, {
    "name" : "probability_of_student",
    "group" : 0.012
  }, {
    "name" : "hint",
    "group" : 0.016
  }, {
    "name" : "new_student",
    "group" : 0.002
  }, {
    "name" : "constraint",
    "group" : 0.006
  }, {
    "name" : "long_term_student",
    "group" : 0.004
  }, {
    "name" : "representation",
    "group" : 0.022
  }, {
    "name" : "ucm_student",
    "group" : 0.003
  }, {
    "name" : "needs_of_student",
    "group" : 0.008
  }, {
    "name" : "interactions_of_student",
    "group" : 0.029
  }, {
    "name" : "success_of_student",
    "group" : 0.006
  }, {
    "name" : "skills_of_student",
    "group" : 0.013
  }, {
    "name" : "performance_of_student",
    "group" : 0.007
  }, {
    "name" : "student_modeling",
    "group" : 0.012
  }, {
    "name" : "518_student",
    "group" : 0.007
  }, {
    "name" : "groups_of_student",
    "group" : 0.008
  }, {
    "name" : "pairs_of_student",
    "group" : 0.005
  }, {
    "name" : "students_exist",
    "group" : 0.002
  }, {
    "name" : "analysis_of_student",
    "group" : 0.005
  }, {
    "name" : "modeling_student",
    "group" : 0.005
  }, {
    "name" : "researcher",
    "group" : 0.059
  }, {
    "name" : "model_student",
    "group" : 0.004
  }, {
    "name" : "program",
    "group" : 0.022
  }, {
    "name" : "unsuccessful_student",
    "group" : 0.002
  }, {
    "name" : "portion_of_student",
    "group" : 0.003
  }, {
    "name" : "edm_method",
    "group" : 0.007
  }, {
    "name" : "general_student",
    "group" : 0.002
  }, {
    "name" : "assessment_of_student",
    "group" : 0.003
  }, {
    "name" : "progress_of_student",
    "group" : 0.003
  }, {
    "name" : "states_of_student",
    "group" : 0.003
  }, {
    "name" : "investigation_of_flawed_parts_of_model",
    "group" : 0.003
  }, {
    "name" : "total_of_student",
    "group" : 0.003
  }, {
    "name" : "group_of_student",
    "group" : 0.005
  }, {
    "name" : "medical_student",
    "group" : 0.002
  }, {
    "name" : "nite_amount_of_opportunity",
    "group" : 0.002
  }, {
    "name" : "models_of_student",
    "group" : 0.007
  }, {
    "name" : "discipline_student",
    "group" : 0.002
  }, {
    "name" : "contribution_of_student",
    "group" : 0.003
  }, {
    "name" : "learning_of_student",
    "group" : 0.003
  }, {
    "name" : "use_of_internet",
    "group" : 0.007
  }, {
    "name" : "data_of_student",
    "group" : 0.004
  }, {
    "name" : "awareness",
    "group" : 0.002
  }, {
    "name" : "measures_of_student",
    "group" : 0.003
  }, {
    "name" : "assessing_student",
    "group" : 0.007
  }, {
    "name" : "level_of_student",
    "group" : 0.003
  }, {
    "name" : "files_of_student",
    "group" : 0.003
  }, {
    "name" : "profiles_of_student",
    "group" : 0.003
  }, {
    "name" : "monitoring_of_stress",
    "group" : 0.008
  }, {
    "name" : "behavior_of_student",
    "group" : 0.003
  }, {
    "name" : "part_of_student",
    "group" : 0.003
  }, {
    "name" : "education_student",
    "group" : 0.007
  }, {
    "name" : "infrastructure",
    "group" : 0.006
  }, {
    "name" : "introductory_computer_science_student",
    "group" : 0.002
  }, {
    "name" : "simulated_student",
    "group" : 0.002
  }, {
    "name" : "value_of_student",
    "group" : 0.003
  }, {
    "name" : "profile_of_student",
    "group" : 0.003
  }, {
    "name" : "proportion_of_student",
    "group" : 0.005
  }, {
    "name" : "stage_of_student",
    "group" : 0.003
  }, {
    "name" : "high_amounts_of_unconstrained_action",
    "group" : 0.005
  }, {
    "name" : "participation_of_student",
    "group" : 0.005
  }, {
    "name" : "record_of_student",
    "group" : 0.003
  }, {
    "name" : "footprints_of_student",
    "group" : 0.003
  }, {
    "name" : "students_likely",
    "group" : 0.012
  }, {
    "name" : "university_student",
    "group" : 0.002
  }, {
    "name" : "terpretable_model",
    "group" : 0.007
  }, {
    "name" : "analysis_technique",
    "group" : 0.005
  }, {
    "name" : "sequences_of_educational_content",
    "group" : 0.003
  }, {
    "name" : "ficult",
    "group" : 0.001
  }, {
    "name" : "dif",
    "group" : 0.001
  }, {
    "name" : "assignments_asynchronously",
    "group" : 0.001
  }, {
    "name" : "access",
    "group" : 0.003
  }, {
    "name" : "staff",
    "group" : 0.005
  }, {
    "name" : "operation_aries",
    "group" : 0.001
  }, {
    "name" : "subject",
    "group" : 0.006
  }, {
    "name" : "competition",
    "group" : 0.002
  }, {
    "name" : "procedure",
    "group" : 0.009
  }, {
    "name" : "lessen",
    "group" : 0.001
  }, {
    "name" : "internet",
    "group" : 0.002
  }, {
    "name" : "double_problem",
    "group" : 0.001
  }, {
    "name" : "logic",
    "group" : 0.006
  }, {
    "name" : "contrary",
    "group" : 0.001
  }, {
    "name" : "group",
    "group" : 0.012
  }, {
    "name" : "opinion",
    "group" : 0.001
  }, {
    "name" : "reasoning",
    "group" : 0.002
  }, {
    "name" : "increase",
    "group" : 0.003
  }, {
    "name" : "computer_session",
    "group" : 0.001
  }, {
    "name" : "contextual_estimation_of_probability",
    "group" : 0.001
  }, {
    "name" : "20_intelligent_tutor_unit",
    "group" : 0.001
  }, {
    "name" : "three_training_module",
    "group" : 0.001
  }, {
    "name" : "help",
    "group" : 0.006
  }, {
    "name" : "four_practice_problem",
    "group" : 0.001
  }, {
    "name" : "basis_of_moodle_forum_usage_datum",
    "group" : 0.002
  }, {
    "name" : "profiles_of_alumni_student",
    "group" : 0.001
  }, {
    "name" : "traditional_way",
    "group" : 0.001
  }, {
    "name" : "instance",
    "group" : 0.002
  }, {
    "name" : "guides_student",
    "group" : 0.002
  }, {
    "name" : "study_of_student",
    "group" : 0.003
  }, {
    "name" : "46_college_student",
    "group" : 0.003
  }, {
    "name" : "scheduling",
    "group" : 0.002
  }, {
    "name" : "constructed from",
    "group" : 0.0
  }, {
    "name" : "clusters_of_student",
    "group" : 0.003
  }, {
    "name" : "weaker_student",
    "group" : 0.009
  }, {
    "name" : "measure_of_student",
    "group" : 0.003
  }, {
    "name" : "behaviors_of_student",
    "group" : 0.003
  }, {
    "name" : "items_skill",
    "group" : 0.011
  }, {
    "name" : "student_success",
    "group" : 0.003
  }, {
    "name" : "actual_state_test_score",
    "group" : 0.005
  }, {
    "name" : "statistically_reliable_improvement",
    "group" : 0.004
  }, {
    "name" : "students_interaction",
    "group" : 0.007
  }, {
    "name" : "concentration_boredom_solely",
    "group" : 0.003
  }, {
    "name" : "practice_schedule",
    "group" : 0.004
  }, {
    "name" : "classification_accuracy",
    "group" : 0.003
  }, {
    "name" : "early_prediction_capability",
    "group" : 0.003
  }, {
    "name" : "knowledge_component_difficulty",
    "group" : 0.003
  }, {
    "name" : "prior_practice",
    "group" : 0.003
  }, {
    "name" : "general_student_proficiency",
    "group" : 0.003
  }, {
    "name" : "performance_factors_analysis_model",
    "group" : 0.001
  }, {
    "name" : "10",
    "group" : 0.0
  }, {
    "name" : "performance_prediction",
    "group" : 0.004
  }, {
    "name" : "multi",
    "group" : 0.0
  }, {
    "name" : "transfer_of_knowledge",
    "group" : 0.007
  }, {
    "name" : "implication",
    "group" : 0.003
  }, {
    "name" : "cognitive_tutor",
    "group" : 0.032
  }, {
    "name" : "student_knowledge",
    "group" : 0.011
  }, {
    "name" : "probability",
    "group" : 0.01
  }, {
    "name" : "parameter",
    "group" : 0.047
  }, {
    "name" : "log",
    "group" : 0.018
  }, {
    "name" : "best_model",
    "group" : 0.006
  }, {
    "name" : "data_model",
    "group" : 0.006
  }, {
    "name" : "bayesian_model",
    "group" : 0.008
  }, {
    "name" : "parameters_of_model",
    "group" : 0.008
  }, {
    "name" : "slip",
    "group" : 0.008
  }, {
    "name" : "underlying_model",
    "group" : 0.005
  }, {
    "name" : "accurate_model",
    "group" : 0.01
  }, {
    "name" : "measurement_model",
    "group" : 0.006
  }, {
    "name" : "educational_data_mining",
    "group" : 0.014
  }, {
    "name" : "improved_model",
    "group" : 0.02
  }, {
    "name" : "school",
    "group" : 0.017
  }, {
    "name" : "existing_cognitive_model",
    "group" : 0.005
  }, {
    "name" : "student_model",
    "group" : 0.028
  }, {
    "name" : "latter_model",
    "group" : 0.006
  }, {
    "name" : "model_of_performance",
    "group" : 0.007
  }, {
    "name" : "alternative_statistical_model",
    "group" : 0.006
  }, {
    "name" : "latent_trait_model",
    "group" : 0.012
  }, {
    "name" : "variations_of_model",
    "group" : 0.008
  }, {
    "name" : "curriculum_model",
    "group" : 0.005
  }, {
    "name" : "combined_cognitive_model",
    "group" : 0.006
  }, {
    "name" : "parts_of_model",
    "group" : 0.007
  }, {
    "name" : "decision_tree_model",
    "group" : 0.006
  }, {
    "name" : "terms_of_ability",
    "group" : 0.01
  }, {
    "name" : "prior_knowledge_model",
    "group" : 0.006
  }, {
    "name" : "students_behavior_model",
    "group" : 0.006
  }, {
    "name" : "effective_student_model",
    "group" : 0.009
  }, {
    "name" : "former_model",
    "group" : 0.006
  }, {
    "name" : "topic_model",
    "group" : 0.007
  }, {
    "name" : "formal_cognitive_diagnosis_model",
    "group" : 0.008
  }, {
    "name" : "hidden_markov_model",
    "group" : 0.007
  }, {
    "name" : "afm_model",
    "group" : 0.008
  }, {
    "name" : "preliminary_model",
    "group" : 0.006
  }, {
    "name" : "dimensional_model",
    "group" : 0.012
  }, {
    "name" : "categorical_model",
    "group" : 0.011
  }, {
    "name" : "student_skill_model",
    "group" : 0.006
  }, {
    "name" : "individual_model",
    "group" : 0.006
  }, {
    "name" : "model_of_misconception",
    "group" : 0.008
  }, {
    "name" : "model_of_learn",
    "group" : 0.008
  }, {
    "name" : "model_of_component",
    "group" : 0.006
  }, {
    "name" : "population_model",
    "group" : 0.005
  }, {
    "name" : "models_of_guess",
    "group" : 0.006
  }, {
    "name" : "could be used to flag",
    "group" : 0.0
  }, {
    "name" : "possible_mediation_model",
    "group" : 0.005
  }, {
    "name" : "comparison_of_model",
    "group" : 0.006
  }, {
    "name" : "learning_method",
    "group" : 0.008
  }, {
    "name" : "simple_model",
    "group" : 0.005
  }, {
    "name" : "poster",
    "group" : 0.012
  }, {
    "name" : "record_students_action",
    "group" : 0.006
  }, {
    "name" : "discovered_model",
    "group" : 0.007
  }, {
    "name" : "cognitive_model",
    "group" : 0.01
  }, {
    "name" : "variety_of_student_speech_act",
    "group" : 0.001
  }, {
    "name" : "assumption",
    "group" : 0.003
  }, {
    "name" : "example",
    "group" : 0.008
  }, {
    "name" : "confusion",
    "group" : 0.001
  }, {
    "name" : "frustration",
    "group" : 0.001
  }, {
    "name" : "predictor_of_students_learn",
    "group" : 0.001
  }, {
    "name" : "one_signi",
    "group" : 0.001
  }, {
    "name" : "best_individual_model",
    "group" : 0.005
  }, {
    "name" : "machine_learning_model",
    "group" : 0.006
  }, {
    "name" : "simple_statistical_model",
    "group" : 0.008
  }, {
    "name" : "empirical_studies_vary",
    "group" : 0.006
  }, {
    "name" : "validation_of_model",
    "group" : 0.006
  }, {
    "name" : "actual_student_model",
    "group" : 0.005
  }, {
    "name" : "development_of_model",
    "group" : 0.006
  }, {
    "name" : "class_of_model",
    "group" : 0.006
  }, {
    "name" : "causal_model",
    "group" : 0.006
  }, {
    "name" : "classifier_model",
    "group" : 0.005
  }, {
    "name" : "curriculum_model_extension",
    "group" : 0.007
  }, {
    "name" : "change_point_model",
    "group" : 0.005
  }, {
    "name" : "model_of_solution",
    "group" : 0.007
  }, {
    "name" : "pedagogical_model",
    "group" : 0.005
  }, {
    "name" : "user_modeling_community",
    "group" : 0.007
  }, {
    "name" : "original_student_model",
    "group" : 0.005
  }, {
    "name" : "improvement_of_model",
    "group" : 0.006
  }, {
    "name" : "irt_model",
    "group" : 0.005
  }, {
    "name" : "logistic_regression_student_model",
    "group" : 0.005
  }, {
    "name" : "linear_model",
    "group" : 0.005
  }, {
    "name" : "complete_academic_curriculum_model",
    "group" : 0.005
  }, {
    "name" : "standard_kt_model",
    "group" : 0.007
  }, {
    "name" : "cognitive_tutor_lesson_variation_space",
    "group" : 0.005
  }, {
    "name" : "accuracy_of_model",
    "group" : 0.006
  }, {
    "name" : "evaluation_of_model",
    "group" : 0.006
  }, {
    "name" : "supervised_machine",
    "group" : 0.007
  }, {
    "name" : "two_new_logistic_regression_model",
    "group" : 0.005
  }, {
    "name" : "students_mental_model",
    "group" : 0.005
  }, {
    "name" : "construction_of_model",
    "group" : 0.006
  }, {
    "name" : "dynamical_systems_model",
    "group" : 0.005
  }, {
    "name" : "representing_domain_knowledge",
    "group" : 0.011
  }, {
    "name" : "lims_event_capture_model",
    "group" : 0.007
  }, {
    "name" : "complicated_uninterpretable_model",
    "group" : 0.005
  }, {
    "name" : "approximation_of_model",
    "group" : 0.006
  }, {
    "name" : "graphical_model",
    "group" : 0.005
  }, {
    "name" : "analysis_of_model",
    "group" : 0.006
  }, {
    "name" : "time_series_model",
    "group" : 0.007
  }, {
    "name" : "obtained_classification_model",
    "group" : 0.005
  }, {
    "name" : "rfr_model",
    "group" : 0.006
  }, {
    "name" : "cognitive_diagnosis_model",
    "group" : 0.007
  }, {
    "name" : "performance_of_model",
    "group" : 0.006
  }, {
    "name" : "individualization_model",
    "group" : 0.006
  }, {
    "name" : "function_of_model",
    "group" : 0.006
  }, {
    "name" : "performances_of_model",
    "group" : 0.006
  }, {
    "name" : "conception_of_model",
    "group" : 0.006
  }, {
    "name" : "implementations_of_model",
    "group" : 0.006
  }, {
    "name" : "models_of_behavior",
    "group" : 0.006
  }, {
    "name" : "differential_student_knowledge_model",
    "group" : 0.005
  }, {
    "name" : "versions_of_model",
    "group" : 0.006
  }, {
    "name" : "inference_procedure",
    "group" : 0.008
  }, {
    "name" : "observed_program_model",
    "group" : 0.005
  }, {
    "name" : "tional_parameter",
    "group" : 0.006
  }, {
    "name" : "contextual_model",
    "group" : 0.005
  }, {
    "name" : "automated_approach",
    "group" : 0.011
  }, {
    "name" : "estimation_of_model",
    "group" : 0.006
  }, {
    "name" : "current_cognitive_model",
    "group" : 0.005
  }, {
    "name" : "model_of_design",
    "group" : 0.006
  }, {
    "name" : "separate_model",
    "group" : 0.006
  }, {
    "name" : "open_student_model",
    "group" : 0.005
  }, {
    "name" : "refined_model",
    "group" : 0.006
  }, {
    "name" : "pre_model",
    "group" : 0.005
  }, {
    "name" : "dirichlet_prior",
    "group" : 0.007
  }, {
    "name" : "trained_model",
    "group" : 0.007
  }, {
    "name" : "good_student_model",
    "group" : 0.006
  }, {
    "name" : "descriptive_model",
    "group" : 0.005
  }, {
    "name" : "subset_of_model",
    "group" : 0.006
  }, {
    "name" : "directory_hierarchy",
    "group" : 0.003
  }, {
    "name" : "numerical_analysis",
    "group" : 0.018
  }, {
    "name" : "common_pattern",
    "group" : 0.006
  }, {
    "name" : "learner_online_engagement",
    "group" : 0.003
  }, {
    "name" : "course_material",
    "group" : 0.004
  }, {
    "name" : "missing_value",
    "group" : 0.006
  }, {
    "name" : "u",
    "group" : 0.0
  }, {
    "name" : "association_rule",
    "group" : 0.003
  }, {
    "name" : "log_file",
    "group" : 0.004
  }, {
    "name" : "collaborative",
    "group" : 0.028
  }, {
    "name" : "university_server",
    "group" : 0.004
  }, {
    "name" : "student_action",
    "group" : 0.009
  }, {
    "name" : "cluster",
    "group" : 0.031
  }, {
    "name" : "technique",
    "group" : 0.044
  }, {
    "name" : "algorithm",
    "group" : 0.059
  }, {
    "name" : "student_datum",
    "group" : 0.012
  }, {
    "name" : "historical_student_datum",
    "group" : 0.004
  }, {
    "name" : "work",
    "group" : 0.062
  }, {
    "name" : "intermediate_datum",
    "group" : 0.004
  }, {
    "name" : "historical_datum",
    "group" : 0.004
  }, {
    "name" : "real_datum",
    "group" : 0.013
  }, {
    "name" : "fmri_datum",
    "group" : 0.004
  }, {
    "name" : "collecting_user_activity_datum",
    "group" : 0.003
  }, {
    "name" : "raw_datum",
    "group" : 0.002
  }, {
    "name" : "quantity_of_datum",
    "group" : 0.005
  }, {
    "name" : "knowledge_tracing_model",
    "group" : 0.019
  }, {
    "name" : "educational_datum",
    "group" : 0.01
  }, {
    "name" : "test_datum",
    "group" : 0.003
  }, {
    "name" : "training_datum",
    "group" : 0.008
  }, {
    "name" : "retrospective_datum",
    "group" : 0.002
  }, {
    "name" : "edm_tool",
    "group" : 0.005
  }, {
    "name" : "unseen_datum",
    "group" : 0.002
  }, {
    "name" : "future_investigation",
    "group" : 0.007
  }, {
    "name" : "raw_student_messaging_datum",
    "group" : 0.003
  }, {
    "name" : "authentic_datum",
    "group" : 0.008
  }, {
    "name" : "simulated_datum",
    "group" : 0.006
  }, {
    "name" : "flood_of_datum",
    "group" : 0.005
  }, {
    "name" : "subjective_datum",
    "group" : 0.003
  }, {
    "name" : "simulate_student_performance_datum",
    "group" : 0.004
  }, {
    "name" : "correctness_performance_datum",
    "group" : 0.004
  }, {
    "name" : "students_response_datum",
    "group" : 0.003
  }, {
    "name" : "wealth_of_datum",
    "group" : 0.005
  }, {
    "name" : "log_file_datum",
    "group" : 0.008
  }, {
    "name" : "lack_of_datum",
    "group" : 0.003
  }, {
    "name" : "unbalanced_datum",
    "group" : 0.002
  }, {
    "name" : "observed_datum",
    "group" : 0.003
  }, {
    "name" : "mining_tutor_datum",
    "group" : 0.002
  }, {
    "name" : "pittsburgh_science_of_learning_center_datashop",
    "group" : 0.002
  }, {
    "name" : "assistments_datum",
    "group" : 0.002
  }, {
    "name" : "amounts_of_datum",
    "group" : 0.003
  }, {
    "name" : "exploration_of_datum",
    "group" : 0.003
  }, {
    "name" : "dirichlet",
    "group" : 0.004
  }, {
    "name" : "deal_of_datum",
    "group" : 0.003
  }, {
    "name" : "experimental_datum",
    "group" : 0.002
  }, {
    "name" : "student_usage_datum",
    "group" : 0.002
  }, {
    "name" : "structure_datum",
    "group" : 0.002
  }, {
    "name" : "characteristics_of_datum",
    "group" : 0.003
  }, {
    "name" : "traditional_datum",
    "group" : 0.002
  }, {
    "name" : "behavior_datum",
    "group" : 0.002
  }, {
    "name" : "multilevel_bayesian_implementations_of_model",
    "group" : 0.003
  }, {
    "name" : "defined_skill",
    "group" : 0.011
  }, {
    "name" : "assessment_datum",
    "group" : 0.002
  }, {
    "name" : "modeling_empirical_student_datum",
    "group" : 0.002
  }, {
    "name" : "continuous_datum",
    "group" : 0.006
  }, {
    "name" : "initial_datum",
    "group" : 0.002
  }, {
    "name" : "moodle_usage_datum",
    "group" : 0.002
  }, {
    "name" : "analysis_of_datum",
    "group" : 0.003
  }, {
    "name" : "hidden_markov_model_methodology",
    "group" : 0.006
  }, {
    "name" : "scalable_datum",
    "group" : 0.002
  }, {
    "name" : "current_student_datum",
    "group" : 0.002
  }, {
    "name" : "student_performance_datum",
    "group" : 0.002
  }, {
    "name" : "mine_educational_datum",
    "group" : 0.006
  }, {
    "name" : "label_datum",
    "group" : 0.002
  }, {
    "name" : "single_empirical_parameter",
    "group" : 0.003
  }, {
    "name" : "admission_datum",
    "group" : 0.003
  }, {
    "name" : "amount_of_datum",
    "group" : 0.003
  }, {
    "name" : "problem_attempt_datum",
    "group" : 0.002
  }, {
    "name" : "trace_datum",
    "group" : 0.004
  }, {
    "name" : "study_of_datum",
    "group" : 0.003
  }, {
    "name" : "students_test_datum",
    "group" : 0.003
  }, {
    "name" : "eleven_educational_technology_datum",
    "group" : 0.002
  }, {
    "name" : "affect_transition_datum",
    "group" : 0.002
  }, {
    "name" : "explorations_of_datum",
    "group" : 0.003
  }, {
    "name" : "integrated_datum",
    "group" : 0.002
  }, {
    "name" : "original_numerical_datum",
    "group" : 0.002
  }, {
    "name" : "rich_feature",
    "group" : 0.007
  }, {
    "name" : "volumes_of_datum",
    "group" : 0.003
  }, {
    "name" : "consideration_students_response_datum",
    "group" : 0.002
  }, {
    "name" : "subset_of_datum",
    "group" : 0.003
  }, {
    "name" : "children_oral_reading_fluency_datum",
    "group" : 0.003
  }, {
    "name" : "log_datum",
    "group" : 0.002
  }, {
    "name" : "web_analytics_datum",
    "group" : 0.002
  }, {
    "name" : "structure_of_datum",
    "group" : 0.003
  }, {
    "name" : "published_datum",
    "group" : 0.004
  }, {
    "name" : "three_baseline",
    "group" : 0.002
  }, {
    "name" : "text_replay_datum",
    "group" : 0.003
  }, {
    "name" : "testing_datum",
    "group" : 0.002
  }, {
    "name" : "basis_of_datum",
    "group" : 0.003
  }, {
    "name" : "rebalancing_datum",
    "group" : 0.002
  }, {
    "name" : "students_online_tutoring_datum",
    "group" : 0.006
  }, {
    "name" : "referenced_datum",
    "group" : 0.002
  }, {
    "name" : "reason",
    "group" : 0.002
  }, {
    "name" : "project_listen_reading_tutor",
    "group" : 0.003
  }, {
    "name" : "practice",
    "group" : 0.006
  }, {
    "name" : "online_assessment_of_student",
    "group" : 0.001
  }, {
    "name" : "account_datum",
    "group" : 0.002
  }, {
    "name" : "modeling_datum",
    "group" : 0.002
  }, {
    "name" : "source_of_datum",
    "group" : 0.003
  }, {
    "name" : "usage_datum",
    "group" : 0.003
  }, {
    "name" : "tutor_datum",
    "group" : 0.002
  }, {
    "name" : "data_of_type",
    "group" : 0.003
  }, {
    "name" : "corpus_of_datum",
    "group" : 0.003
  }, {
    "name" : "pair_of_datum",
    "group" : 0.003
  }, {
    "name" : "individual_item",
    "group" : 0.003
  }, {
    "name" : "user_model_mapping",
    "group" : 0.003
  }, {
    "name" : "collaborative_experience",
    "group" : 0.003
  }, {
    "name" : "possible_pair",
    "group" : 0.0
  }, {
    "name" : "fast_alternate_approach",
    "group" : 0.004
  }, {
    "name" : "intelligent_tutor",
    "group" : 0.004
  }, {
    "name" : "decomposition",
    "group" : 0.007
  }, {
    "name" : "machine",
    "group" : 0.032
  }, {
    "name" : "data_mining_method",
    "group" : 0.011
  }, {
    "name" : "recent_method",
    "group" : 0.004
  }, {
    "name" : "challenge",
    "group" : 0.006
  }, {
    "name" : "novel_method",
    "group" : 0.006
  }, {
    "name" : "popular_educational_data_mining_method",
    "group" : 0.004
  }, {
    "name" : "knowledge_diagnosis_method",
    "group" : 0.001
  }, {
    "name" : "powerful_method",
    "group" : 0.004
  }, {
    "name" : "educational_data_mining_method",
    "group" : 0.003
  }, {
    "name" : "learn",
    "group" : 0.055
  }, {
    "name" : "variety_of_method",
    "group" : 0.002
  }, {
    "name" : "previous_method",
    "group" : 0.003
  }, {
    "name" : "bayesian_method",
    "group" : 0.001
  }, {
    "name" : "empty_paper",
    "group" : 0.004
  }, {
    "name" : "new_method",
    "group" : 0.001
  }, {
    "name" : "final_mark",
    "group" : 0.01
  }, {
    "name" : "six_estimation_method",
    "group" : 0.001
  }, {
    "name" : "extension_of_method",
    "group" : 0.002
  }, {
    "name" : "integrated_view_of_student_effort",
    "group" : 0.001
  }, {
    "name" : "real_way",
    "group" : 0.001
  }, {
    "name" : "wise dependency relationships in",
    "group" : 0.0
  }, {
    "name" : "digital_footprints_of_student",
    "group" : 0.003
  }, {
    "name" : "ten_of_eleven_case",
    "group" : 0.001
  }, {
    "name" : "language_learn",
    "group" : 0.001
  }, {
    "name" : "requirement_of_method",
    "group" : 0.002
  }, {
    "name" : "categories_of_method",
    "group" : 0.002
  }, {
    "name" : "standard_validation_method",
    "group" : 0.002
  }, {
    "name" : "feasibility_of_method",
    "group" : 0.002
  }, {
    "name" : "prediction_of_method",
    "group" : 0.002
  }, {
    "name" : "assumptions_of_method",
    "group" : 0.003
  }, {
    "name" : "evaluation_of_method",
    "group" : 0.002
  }, {
    "name" : "simple_method",
    "group" : 0.002
  }, {
    "name" : "students_possible_solution_method",
    "group" : 0.001
  }, {
    "name" : "faithfulness_of_method",
    "group" : 0.002
  }, {
    "name" : "introduction_of_method",
    "group" : 0.002
  }, {
    "name" : "recommender_system",
    "group" : 0.006
  }, {
    "name" : "generality_of_hidden_markov_model_approach",
    "group" : 0.001
  }, {
    "name" : "evaluation_of_bayesian_model_of_student_misconception",
    "group" : 0.001
  }, {
    "name" : "development_of_dynamical_systems_model_of_self",
    "group" : 0.0
  }, {
    "name" : "exploratory_analysis",
    "group" : 0.004
  }, {
    "name" : "enabling_step",
    "group" : 0.002
  }, {
    "name" : "light",
    "group" : 0.003
  }, {
    "name" : "hybrid_recommender_system",
    "group" : 0.006
  }, {
    "name" : "course_mark",
    "group" : 0.003
  }, {
    "name" : "introductory_computer_science_course",
    "group" : 0.007
  }, {
    "name" : "results_of_pilot_study",
    "group" : 0.003
  }, {
    "name" : "exploratory_data_mining_methodology",
    "group" : 0.003
  }, {
    "name" : "novel_computational",
    "group" : 0.003
  }, {
    "name" : "collaborative_educational_data_mining_tool",
    "group" : 0.012
  }, {
    "name" : "laborious_task",
    "group" : 0.004
  }, {
    "name" : "effect_of_stream",
    "group" : 0.005
  }, {
    "name" : "comparative_study_of_datum",
    "group" : 0.012
  }, {
    "name" : "first",
    "group" : 0.0
  }, {
    "name" : "novel_approach",
    "group" : 0.008
  }, {
    "name" : "finding",
    "group" : 0.006
  }, {
    "name" : "data_mining_approach",
    "group" : 0.014
  }, {
    "name" : "data_mining_technique",
    "group" : 0.014
  }, {
    "name" : "purpose",
    "group" : 0.009
  }, {
    "name" : "study",
    "group" : 0.054
  }, {
    "name" : "visualization",
    "group" : 0.006
  }, {
    "name" : "environmental_science",
    "group" : 0.004
  }, {
    "name" : "analysis_techniques_of_nmf_output",
    "group" : 0.005
  }, {
    "name" : "generation_of_domain_variable",
    "group" : 0.001
  }, {
    "name" : "context",
    "group" : 0.01
  }, {
    "name" : "contrast",
    "group" : 0.001
  }, {
    "name" : "public_release_of_corpus_of_million_translations_of_natural_language_nl_sentence",
    "group" : 0.001
  }, {
    "name" : "study_of_student_assessment_datum",
    "group" : 0.001
  }, {
    "name" : "application_of_formal_concept_analysis",
    "group" : 0.001
  }, {
    "name" : "newcomer",
    "group" : 0.001
  }, {
    "name" : "expert",
    "group" : 0.006
  }, {
    "name" : "student_evaluation_of_teaching",
    "group" : 0.001
  }, {
    "name" : "preliminary_analysis_of_student_question",
    "group" : 0.001
  }, {
    "name" : "development_of_two_related_machine",
    "group" : 0.0
  }, {
    "name" : "use_of_meta",
    "group" : 0.0
  }, {
    "name" : "idea",
    "group" : 0.003
  }, {
    "name" : "variety_of_data_mining_approach",
    "group" : 0.001
  }, {
    "name" : "contribution_of_paper",
    "group" : 0.004
  }, {
    "name" : "goal_of_paper",
    "group" : 0.002
  }, {
    "name" : "recent_paper",
    "group" : 0.001
  }, {
    "name" : "engineered_feature",
    "group" : 0.005
  }, {
    "name" : "aim_of_paper",
    "group" : 0.002
  }, {
    "name" : "empty",
    "group" : 0.006
  }, {
    "name" : "grammar_guided_genetic_programming_algorithm",
    "group" : 0.004
  }, {
    "name" : "master_program",
    "group" : 0.01
  }, {
    "name" : "automated_feedback",
    "group" : 0.004
  }, {
    "name" : "investigation",
    "group" : 0.033
  }, {
    "name" : "management_system",
    "group" : 0.008
  }, {
    "name" : "automated_tutoring_system",
    "group" : 0.006
  }, {
    "name" : "rpm_system",
    "group" : 0.004
  }, {
    "name" : "reading_strategy",
    "group" : 0.007
  }, {
    "name" : "adaptive_educational_system",
    "group" : 0.006
  }, {
    "name" : "gaming_system",
    "group" : 0.006
  }, {
    "name" : "sword_system",
    "group" : 0.006
  }, {
    "name" : "software_version_control_system",
    "group" : 0.009
  }, {
    "name" : "peer_production_educational_system",
    "group" : 0.004
  }, {
    "name" : "construction_of_system",
    "group" : 0.006
  }, {
    "name" : "course_management_system",
    "group" : 0.004
  }, {
    "name" : "modules_of_system",
    "group" : 0.005
  }, {
    "name" : "tutor_system",
    "group" : 0.004
  }, {
    "name" : "geographic_information_system",
    "group" : 0.004
  }, {
    "name" : "behavior_of_system",
    "group" : 0.006
  }, {
    "name" : "automated_grading_system",
    "group" : 0.005
  }, {
    "name" : "learning_system",
    "group" : 0.004
  }, {
    "name" : "moodle_system",
    "group" : 0.004
  }, {
    "name" : "assistment_system",
    "group" : 0.004
  }, {
    "name" : "educational_system",
    "group" : 0.005
  }, {
    "name" : "ability_of_system",
    "group" : 0.006
  }, {
    "name" : "automatic_grading_system",
    "group" : 0.005
  }, {
    "name" : "information_system",
    "group" : 0.004
  }, {
    "name" : "reflection",
    "group" : 0.001
  }, {
    "name" : "mechanism",
    "group" : 0.003
  }, {
    "name" : "flashcard_system",
    "group" : 0.004
  }, {
    "name" : "adaptation_of_system",
    "group" : 0.005
  }, {
    "name" : "spaced_practice_effect",
    "group" : 0.004
  }, {
    "name" : "linguistic_knowledge",
    "group" : 0.004
  }, {
    "name" : "pedagogical_knowledge",
    "group" : 0.004
  }, {
    "name" : "student_cognitive",
    "group" : 0.005
  }, {
    "name" : "hypothesis",
    "group" : 0.007
  }, {
    "name" : "affective_state",
    "group" : 0.011
  }, {
    "name" : "instruction",
    "group" : 0.01
  }, {
    "name" : "unexpected_result",
    "group" : 0.028
  }, {
    "name" : "global_prediction_result",
    "group" : 0.004
  }, {
    "name" : "corbett",
    "group" : 0.005
  }, {
    "name" : "teacher",
    "group" : 0.03
  }, {
    "name" : "results_of_methodology",
    "group" : 0.004
  }, {
    "name" : "clustering_result",
    "group" : 0.001
  }, {
    "name" : "prior_result",
    "group" : 0.001
  }, {
    "name" : "experimental_result",
    "group" : 0.001
  }, {
    "name" : "results_of_analysis",
    "group" : 0.003
  }, {
    "name" : "result_of_analysis_of_student",
    "group" : 0.002
  }, {
    "name" : "results_of_assessment",
    "group" : 0.002
  }, {
    "name" : "exploratory_result",
    "group" : 0.001
  }, {
    "name" : "support_of_result",
    "group" : 0.002
  }, {
    "name" : "results_of_simulation",
    "group" : 0.002
  }, {
    "name" : "meaningful_result",
    "group" : 0.001
  }, {
    "name" : "previous_result",
    "group" : 0.001
  }, {
    "name" : "teamwork_result",
    "group" : 0.005
  }, {
    "name" : "preliminary_result",
    "group" : 0.004
  }, {
    "name" : "test_result",
    "group" : 0.001
  }, {
    "name" : "results_of_mining",
    "group" : 0.002
  }, {
    "name" : "bhatnagar",
    "group" : 0.002
  }, {
    "name" : "two_region",
    "group" : 0.001
  }, {
    "name" : "bifurcation",
    "group" : 0.001
  }, {
    "name" : "potential_of_iterative_methodology",
    "group" : 0.001
  }, {
    "name" : "show",
    "group" : 0.001
  }, {
    "name" : "evidence",
    "group" : 0.003
  }, {
    "name" : "assessment_result",
    "group" : 0.002
  }, {
    "name" : "new_domain_model_result",
    "group" : 0.001
  }, {
    "name" : "initial_result",
    "group" : 0.006
  }, {
    "name" : "analysis_of_result",
    "group" : 0.003
  }, {
    "name" : "results_of_study",
    "group" : 0.002
  }, {
    "name" : "results_of_algorithm",
    "group" : 0.002
  }, {
    "name" : "educational_data_mining_field",
    "group" : 0.003
  }, {
    "name" : "model_transfer",
    "group" : 0.003
  }, {
    "name" : "identification_of_behavior",
    "group" : 0.005
  }, {
    "name" : "widely_used_subset_of_item_response_theory_model",
    "group" : 0.007
  }, {
    "name" : "data_mining",
    "group" : 0.012
  }, {
    "name" : "classification",
    "group" : 0.011
  }, {
    "name" : "association_analysis",
    "group" : 0.003
  }, {
    "name" : "interactive_approach",
    "group" : 0.003
  }, {
    "name" : "simulation_approach",
    "group" : 0.004
  }, {
    "name" : "proposed_approach",
    "group" : 0.007
  }, {
    "name" : "widely_used_approach",
    "group" : 0.004
  }, {
    "name" : "core_of_approach",
    "group" : 0.004
  }, {
    "name" : "traditional_approach",
    "group" : 0.006
  }, {
    "name" : "student_modeling_approach",
    "group" : 0.015
  }, {
    "name" : "practicality_of_approach",
    "group" : 0.002
  }, {
    "name" : "underlying_structure",
    "group" : 0.001
  }, {
    "name" : "conventional_approach",
    "group" : 0.009
  }, {
    "name" : "compensatory_approach",
    "group" : 0.001
  }, {
    "name" : "causal_modeling_approach",
    "group" : 0.001
  }, {
    "name" : "new_cognitive_modeling_approach",
    "group" : 0.001
  }, {
    "name" : "generality_of_approach",
    "group" : 0.002
  }, {
    "name" : "simple_approach",
    "group" : 0.002
  }, {
    "name" : "usage_of_approach",
    "group" : 0.002
  }, {
    "name" : "have_variety_of_approach",
    "group" : 0.002
  }, {
    "name" : "advantages_of_approach",
    "group" : 0.002
  }, {
    "name" : "promising_approach",
    "group" : 0.001
  }, {
    "name" : "preliminary_data_mining_approach",
    "group" : 0.001
  }, {
    "name" : "clustering_approach",
    "group" : 0.001
  }, {
    "name" : "ed_approach",
    "group" : 0.005
  }, {
    "name" : "mining_approach",
    "group" : 0.003
  }, {
    "name" : "conjunctive_approach",
    "group" : 0.001
  }, {
    "name" : "version_of_approach",
    "group" : 0.003
  }, {
    "name" : "variety_of_approach",
    "group" : 0.002
  }, {
    "name" : "early_stage",
    "group" : 0.003
  }, {
    "name" : "weakness_of_skill",
    "group" : 0.012
  }, {
    "name" : "modelled_skill",
    "group" : 0.009
  }, {
    "name" : "groups_of_skill",
    "group" : 0.016
  }, {
    "name" : "learner_skill",
    "group" : 0.011
  }, {
    "name" : "latent_skill",
    "group" : 0.021
  }, {
    "name" : "learning_skill",
    "group" : 0.024
  }, {
    "name" : "pre",
    "group" : 0.011
  }, {
    "name" : "introduction_of_automatic_subspace_clustering_method",
    "group" : 0.009
  }, {
    "name" : "assignment_of_skill",
    "group" : 0.011
  }, {
    "name" : "detectors_of_skill",
    "group" : 0.011
  }, {
    "name" : "student_argument_skill",
    "group" : 0.009
  }, {
    "name" : "strength_of_skill",
    "group" : 0.011
  }, {
    "name" : "complexities_of_skill",
    "group" : 0.011
  }, {
    "name" : "one_important_class_of_feature",
    "group" : 0.011
  }, {
    "name" : "examinees_skill",
    "group" : 0.009
  }, {
    "name" : "students_skill",
    "group" : 0.009
  }, {
    "name" : "algebra_skill",
    "group" : 0.009
  }, {
    "name" : "capability_matrix",
    "group" : 0.013
  }, {
    "name" : "development_of_skill",
    "group" : 0.011
  }, {
    "name" : "student_skill",
    "group" : 0.013
  }, {
    "name" : "composition_of_skill",
    "group" : 0.011
  }, {
    "name" : "assumption_of_skill",
    "group" : 0.011
  }, {
    "name" : "response_time",
    "group" : 0.001
  }, {
    "name" : "characteristic_learning_behavior",
    "group" : 0.004
  }, {
    "name" : "strategy",
    "group" : 0.015
  }, {
    "name" : "analysis_of_map",
    "group" : 0.004
  }, {
    "name" : "data_analysis",
    "group" : 0.004
  }, {
    "name" : "social_networks_analysis",
    "group" : 0.001
  }, {
    "name" : "exploratory_sequence_analysis",
    "group" : 0.001
  }, {
    "name" : "models_analysis",
    "group" : 0.003
  }, {
    "name" : "syntactical_analysis",
    "group" : 0.001
  }, {
    "name" : "preliminary_analysis",
    "group" : 0.004
  }, {
    "name" : "analyses_of_process",
    "group" : 0.004
  }, {
    "name" : "analysis_of_prediction",
    "group" : 0.003
  }, {
    "name" : "analysis_of_set",
    "group" : 0.003
  }, {
    "name" : "study_of_analysis",
    "group" : 0.003
  }, {
    "name" : "analysis_of_misclassifications",
    "group" : 0.003
  }, {
    "name" : "analysis_of_score",
    "group" : 0.003
  }, {
    "name" : "linear_discriminant_analysis",
    "group" : 0.003
  }, {
    "name" : "analysis_of_parameters_of_model",
    "group" : 0.003
  }, {
    "name" : "factor_analysis",
    "group" : 0.001
  }, {
    "name" : "attribute_data_analysis",
    "group" : 0.001
  }, {
    "name" : "analysis_of_question",
    "group" : 0.009
  }, {
    "name" : "thorough_analysis",
    "group" : 0.003
  }, {
    "name" : "analyses_of_location",
    "group" : 0.003
  }, {
    "name" : "application_of_analysis",
    "group" : 0.003
  }, {
    "name" : "combination_of_analysis",
    "group" : 0.003
  }, {
    "name" : "addition",
    "group" : 0.003
  }, {
    "name" : "statistical_analysis",
    "group" : 0.001
  }, {
    "name" : "analysis_of_file",
    "group" : 0.003
  } ],
  "links" : [ {
    "source" : 1,
    "target" : 11,
    "value" : 1.0
  }, {
    "source" : 1,
    "target" : 1,
    "value" : 1.0
  }, {
    "source" : 1,
    "target" : 1,
    "value" : 1.0
  }, {
    "source" : 1,
    "target" : 1,
    "value" : 1.0
  }, {
    "source" : 1,
    "target" : 1,
    "value" : 1.0
  }, {
    "source" : 1,
    "target" : 12,
    "value" : 0.5
  }, {
    "source" : 1,
    "target" : 13,
    "value" : 0.5
  }, {
    "source" : 1,
    "target" : 14,
    "value" : 0.5
  }, {
    "source" : 1,
    "target" : 15,
    "value" : 0.5
  }, {
    "source" : 1,
    "target" : 16,
    "value" : 0.5
  }, {
    "source" : 1,
    "target" : 17,
    "value" : 0.5
  }, {
    "source" : 1,
    "target" : 18,
    "value" : 0.5
  }, {
    "source" : 1,
    "target" : 19,
    "value" : 0.5
  }, {
    "source" : 1,
    "target" : 20,
    "value" : 0.5
  }, {
    "source" : 1,
    "target" : 21,
    "value" : 0.5
  }, {
    "source" : 1,
    "target" : 22,
    "value" : 0.5
  }, {
    "source" : 1,
    "target" : 23,
    "value" : 0.5
  }, {
    "source" : 1,
    "target" : 24,
    "value" : 0.5
  }, {
    "source" : 1,
    "target" : 25,
    "value" : 0.5
  }, {
    "source" : 1,
    "target" : 26,
    "value" : 0.5
  }, {
    "source" : 1,
    "target" : 27,
    "value" : 0.5
  }, {
    "source" : 1,
    "target" : 28,
    "value" : 0.5
  }, {
    "source" : 1,
    "target" : 29,
    "value" : 0.5
  }, {
    "source" : 1,
    "target" : 30,
    "value" : 0.5
  }, {
    "source" : 1,
    "target" : 31,
    "value" : 0.5
  }, {
    "source" : 1,
    "target" : 32,
    "value" : 0.5
  }, {
    "source" : 1,
    "target" : 33,
    "value" : 0.5
  }, {
    "source" : 1,
    "target" : 34,
    "value" : 0.5
  }, {
    "source" : 1,
    "target" : 35,
    "value" : 0.5
  }, {
    "source" : 1,
    "target" : 36,
    "value" : 0.5
  }, {
    "source" : 1,
    "target" : 4,
    "value" : 0.333
  }, {
    "source" : 1,
    "target" : 37,
    "value" : 0.333
  }, {
    "source" : 1,
    "target" : 38,
    "value" : 0.333
  }, {
    "source" : 1,
    "target" : 39,
    "value" : 0.333
  }, {
    "source" : 1,
    "target" : 40,
    "value" : 0.333
  }, {
    "source" : 1,
    "target" : 41,
    "value" : 0.333
  }, {
    "source" : 1,
    "target" : 42,
    "value" : 0.333
  }, {
    "source" : 1,
    "target" : 43,
    "value" : 0.333
  }, {
    "source" : 1,
    "target" : 43,
    "value" : 0.333
  }, {
    "source" : 1,
    "target" : 43,
    "value" : 0.333
  }, {
    "source" : 1,
    "target" : 44,
    "value" : 0.333
  }, {
    "source" : 1,
    "target" : 45,
    "value" : 0.333
  }, {
    "source" : 1,
    "target" : 46,
    "value" : 0.25
  }, {
    "source" : 1,
    "target" : 47,
    "value" : 0.25
  }, {
    "source" : 1,
    "target" : 48,
    "value" : 0.25
  }, {
    "source" : 1,
    "target" : 49,
    "value" : 0.222
  }, {
    "source" : 1,
    "target" : 49,
    "value" : 0.222
  }, {
    "source" : 1,
    "target" : 50,
    "value" : 0.208
  }, {
    "source" : 1,
    "target" : 50,
    "value" : 0.208
  }, {
    "source" : 1,
    "target" : 50,
    "value" : 0.208
  }, {
    "source" : 1,
    "target" : 50,
    "value" : 0.208
  }, {
    "source" : 1,
    "target" : 50,
    "value" : 0.208
  }, {
    "source" : 1,
    "target" : 51,
    "value" : 0.2
  }, {
    "source" : 1,
    "target" : 52,
    "value" : 0.2
  }, {
    "source" : 1,
    "target" : 53,
    "value" : 0.2
  }, {
    "source" : 1,
    "target" : 53,
    "value" : 0.2
  }, {
    "source" : 1,
    "target" : 54,
    "value" : 0.167
  }, {
    "source" : 1,
    "target" : 55,
    "value" : 0.154
  }, {
    "source" : 1,
    "target" : 55,
    "value" : 0.154
  }, {
    "source" : 1,
    "target" : 55,
    "value" : 0.154
  }, {
    "source" : 1,
    "target" : 56,
    "value" : 0.143
  }, {
    "source" : 1,
    "target" : 57,
    "value" : 0.143
  }, {
    "source" : 1,
    "target" : 9,
    "value" : 0.13
  }, {
    "source" : 1,
    "target" : 9,
    "value" : 0.13
  }, {
    "source" : 1,
    "target" : 9,
    "value" : 0.13
  }, {
    "source" : 1,
    "target" : 9,
    "value" : 0.13
  }, {
    "source" : 1,
    "target" : 9,
    "value" : 0.13
  }, {
    "source" : 1,
    "target" : 9,
    "value" : 0.13
  }, {
    "source" : 1,
    "target" : 58,
    "value" : 0.111
  }, {
    "source" : 1,
    "target" : 59,
    "value" : 0.111
  }, {
    "source" : 1,
    "target" : 60,
    "value" : 0.1
  }, {
    "source" : 1,
    "target" : 61,
    "value" : 0.1
  }, {
    "source" : 1,
    "target" : 62,
    "value" : 0.083
  }, {
    "source" : 1,
    "target" : 63,
    "value" : 0.083
  }, {
    "source" : 1,
    "target" : 64,
    "value" : 0.077
  }, {
    "source" : 1,
    "target" : 6,
    "value" : 0.073
  }, {
    "source" : 1,
    "target" : 6,
    "value" : 0.073
  }, {
    "source" : 1,
    "target" : 65,
    "value" : 0.071
  }, {
    "source" : 1,
    "target" : 44,
    "value" : 0.056
  }, {
    "source" : 1,
    "target" : 44,
    "value" : 0.056
  }, {
    "source" : 1,
    "target" : 66,
    "value" : 0.045
  }, {
    "source" : 1,
    "target" : 67,
    "value" : 0.032
  }, {
    "source" : 1,
    "target" : 68,
    "value" : 0.028
  }, {
    "source" : 1,
    "target" : 69,
    "value" : 0.025
  }, {
    "source" : 1,
    "target" : 53,
    "value" : 0.022
  }, {
    "source" : 1,
    "target" : 53,
    "value" : 0.022
  }, {
    "source" : 1,
    "target" : 53,
    "value" : 0.022
  }, {
    "source" : 1,
    "target" : 6,
    "value" : 0.017
  }, {
    "source" : 1,
    "target" : 6,
    "value" : 0.017
  }, {
    "source" : 1,
    "target" : 2,
    "value" : 0.016
  }, {
    "source" : 1,
    "target" : 2,
    "value" : 0.013
  }, {
    "source" : 1,
    "target" : 2,
    "value" : 0.013
  }, {
    "source" : 1,
    "target" : 11,
    "value" : 0.009
  }, {
    "source" : 1,
    "target" : 70,
    "value" : 0.004
  }, {
    "source" : 1,
    "target" : 71,
    "value" : 0.004
  }, {
    "source" : 1,
    "target" : 72,
    "value" : 0.004
  }, {
    "source" : 1,
    "target" : 73,
    "value" : 0.004
  }, {
    "source" : 1,
    "target" : 74,
    "value" : 0.004
  }, {
    "source" : 1,
    "target" : 75,
    "value" : 0.004
  }, {
    "source" : 1,
    "target" : 76,
    "value" : 0.004
  }, {
    "source" : 1,
    "target" : 77,
    "value" : 0.004
  }, {
    "source" : 1,
    "target" : 78,
    "value" : 0.004
  }, {
    "source" : 1,
    "target" : 79,
    "value" : 0.004
  }, {
    "source" : 1,
    "target" : 80,
    "value" : 0.004
  }, {
    "source" : 1,
    "target" : 81,
    "value" : 0.004
  }, {
    "source" : 1,
    "target" : 82,
    "value" : 0.004
  }, {
    "source" : 1,
    "target" : 83,
    "value" : 0.004
  }, {
    "source" : 1,
    "target" : 84,
    "value" : 0.004
  }, {
    "source" : 1,
    "target" : 85,
    "value" : 0.004
  }, {
    "source" : 1,
    "target" : 86,
    "value" : 0.004
  }, {
    "source" : 1,
    "target" : 87,
    "value" : 0.004
  }, {
    "source" : 1,
    "target" : 88,
    "value" : 0.004
  }, {
    "source" : 1,
    "target" : 89,
    "value" : 0.004
  }, {
    "source" : 1,
    "target" : 90,
    "value" : 0.004
  }, {
    "source" : 1,
    "target" : 7,
    "value" : 0.004
  }, {
    "source" : 1,
    "target" : 91,
    "value" : 0.004
  }, {
    "source" : 1,
    "target" : 92,
    "value" : 0.004
  }, {
    "source" : 1,
    "target" : 93,
    "value" : 0.004
  }, {
    "source" : 1,
    "target" : 94,
    "value" : 0.004
  }, {
    "source" : 1,
    "target" : 3,
    "value" : 0.004
  }, {
    "source" : 1,
    "target" : 95,
    "value" : 0.004
  }, {
    "source" : 1,
    "target" : 96,
    "value" : 0.004
  }, {
    "source" : 1,
    "target" : 97,
    "value" : 0.004
  }, {
    "source" : 1,
    "target" : 98,
    "value" : 0.004
  }, {
    "source" : 1,
    "target" : 99,
    "value" : 0.0
  }, {
    "source" : 1,
    "target" : 100,
    "value" : 0.0
  }, {
    "source" : 1,
    "target" : 101,
    "value" : 0.0
  }, {
    "source" : 1,
    "target" : 102,
    "value" : 0.0
  }, {
    "source" : 1,
    "target" : 103,
    "value" : 0.0
  }, {
    "source" : 1,
    "target" : 104,
    "value" : 0.0
  }, {
    "source" : 1,
    "target" : 105,
    "value" : 0.0
  }, {
    "source" : 1,
    "target" : 106,
    "value" : 0.0
  }, {
    "source" : 1,
    "target" : 107,
    "value" : 0.0
  }, {
    "source" : 1,
    "target" : 108,
    "value" : 0.0
  }, {
    "source" : 1,
    "target" : 109,
    "value" : 0.0
  }, {
    "source" : 1,
    "target" : 110,
    "value" : 0.0
  }, {
    "source" : 1,
    "target" : 111,
    "value" : 0.0
  }, {
    "source" : 1,
    "target" : 112,
    "value" : 0.0
  }, {
    "source" : 1,
    "target" : 113,
    "value" : 0.0
  }, {
    "source" : 1,
    "target" : 114,
    "value" : 0.0
  }, {
    "source" : 1,
    "target" : 115,
    "value" : 0.0
  }, {
    "source" : 1,
    "target" : 116,
    "value" : 0.0
  }, {
    "source" : 1,
    "target" : 117,
    "value" : 0.0
  }, {
    "source" : 1,
    "target" : 118,
    "value" : 0.0
  }, {
    "source" : 1,
    "target" : 119,
    "value" : 0.0
  }, {
    "source" : 1,
    "target" : 120,
    "value" : 0.0
  }, {
    "source" : 1,
    "target" : 121,
    "value" : 0.0
  }, {
    "source" : 1,
    "target" : 122,
    "value" : 0.0
  }, {
    "source" : 1,
    "target" : 123,
    "value" : 0.0
  }, {
    "source" : 1,
    "target" : 123,
    "value" : 0.0
  }, {
    "source" : 1,
    "target" : 124,
    "value" : 0.0
  }, {
    "source" : 1,
    "target" : 125,
    "value" : 0.0
  }, {
    "source" : 1,
    "target" : 126,
    "value" : 0.0
  }, {
    "source" : 1,
    "target" : 127,
    "value" : 0.0
  }, {
    "source" : 1,
    "target" : 128,
    "value" : 0.0
  }, {
    "source" : 1,
    "target" : 129,
    "value" : 0.0
  }, {
    "source" : 1,
    "target" : 130,
    "value" : 0.0
  }, {
    "source" : 1,
    "target" : 131,
    "value" : 0.0
  }, {
    "source" : 1,
    "target" : 132,
    "value" : 0.0
  }, {
    "source" : 1,
    "target" : 133,
    "value" : 0.0
  }, {
    "source" : 1,
    "target" : 64,
    "value" : 0.0
  }, {
    "source" : 1,
    "target" : 134,
    "value" : 0.0
  }, {
    "source" : 1,
    "target" : 135,
    "value" : 0.0
  }, {
    "source" : 1,
    "target" : 136,
    "value" : 0.0
  }, {
    "source" : 1,
    "target" : 137,
    "value" : 0.0
  }, {
    "source" : 1,
    "target" : 138,
    "value" : 0.0
  }, {
    "source" : 1,
    "target" : 139,
    "value" : 0.0
  }, {
    "source" : 1,
    "target" : 140,
    "value" : 0.0
  }, {
    "source" : 1,
    "target" : 141,
    "value" : 0.0
  }, {
    "source" : 1,
    "target" : 7,
    "value" : 0.0
  }, {
    "source" : 1,
    "target" : 142,
    "value" : 0.0
  }, {
    "source" : 1,
    "target" : 143,
    "value" : 0.0
  }, {
    "source" : 1,
    "target" : 144,
    "value" : 0.0
  }, {
    "source" : 1,
    "target" : 145,
    "value" : 0.0
  }, {
    "source" : 1,
    "target" : 146,
    "value" : 0.0
  }, {
    "source" : 1,
    "target" : 147,
    "value" : 0.0
  }, {
    "source" : 1,
    "target" : 147,
    "value" : 0.0
  }, {
    "source" : 1,
    "target" : 148,
    "value" : 0.0
  }, {
    "source" : 1,
    "target" : 149,
    "value" : 0.0
  }, {
    "source" : 1,
    "target" : 150,
    "value" : 0.0
  }, {
    "source" : 1,
    "target" : 151,
    "value" : 0.0
  }, {
    "source" : 1,
    "target" : 152,
    "value" : 0.0
  }, {
    "source" : 1,
    "target" : 153,
    "value" : 0.0
  }, {
    "source" : 1,
    "target" : 154,
    "value" : 0.0
  }, {
    "source" : 1,
    "target" : 155,
    "value" : 0.0
  }, {
    "source" : 1,
    "target" : 156,
    "value" : 0.0
  }, {
    "source" : 1,
    "target" : 157,
    "value" : 0.0
  }, {
    "source" : 1,
    "target" : 158,
    "value" : 0.0
  }, {
    "source" : 1,
    "target" : 159,
    "value" : 0.0
  }, {
    "source" : 1,
    "target" : 160,
    "value" : 0.0
  }, {
    "source" : 1,
    "target" : 161,
    "value" : 0.0
  }, {
    "source" : 1,
    "target" : 162,
    "value" : 0.0
  }, {
    "source" : 1,
    "target" : 163,
    "value" : 0.0
  }, {
    "source" : 1,
    "target" : 164,
    "value" : 0.0
  }, {
    "source" : 1,
    "target" : 165,
    "value" : 0.0
  }, {
    "source" : 1,
    "target" : 165,
    "value" : 0.0
  }, {
    "source" : 1,
    "target" : 165,
    "value" : 0.0
  }, {
    "source" : 1,
    "target" : 166,
    "value" : 0.0
  }, {
    "source" : 1,
    "target" : 167,
    "value" : 0.0
  }, {
    "source" : 1,
    "target" : 167,
    "value" : 0.0
  }, {
    "source" : 1,
    "target" : 168,
    "value" : 0.0
  }, {
    "source" : 1,
    "target" : 169,
    "value" : 0.0
  }, {
    "source" : 1,
    "target" : 170,
    "value" : 0.0
  }, {
    "source" : 1,
    "target" : 171,
    "value" : 0.0
  }, {
    "source" : 1,
    "target" : 172,
    "value" : 0.0
  }, {
    "source" : 1,
    "target" : 173,
    "value" : 0.0
  }, {
    "source" : 1,
    "target" : 174,
    "value" : 0.0
  }, {
    "source" : 1,
    "target" : 175,
    "value" : 0.0
  }, {
    "source" : 1,
    "target" : 176,
    "value" : 0.0
  }, {
    "source" : 1,
    "target" : 177,
    "value" : 0.0
  }, {
    "source" : 1,
    "target" : 178,
    "value" : 0.0
  }, {
    "source" : 1,
    "target" : 179,
    "value" : 0.0
  }, {
    "source" : 2,
    "target" : 180,
    "value" : 0.5
  }, {
    "source" : 2,
    "target" : 181,
    "value" : 0.5
  }, {
    "source" : 2,
    "target" : 182,
    "value" : 0.5
  }, {
    "source" : 2,
    "target" : 183,
    "value" : 0.5
  }, {
    "source" : 2,
    "target" : 184,
    "value" : 0.5
  }, {
    "source" : 2,
    "target" : 184,
    "value" : 0.5
  }, {
    "source" : 2,
    "target" : 184,
    "value" : 0.5
  }, {
    "source" : 2,
    "target" : 185,
    "value" : 0.5
  }, {
    "source" : 2,
    "target" : 186,
    "value" : 0.5
  }, {
    "source" : 2,
    "target" : 187,
    "value" : 0.5
  }, {
    "source" : 2,
    "target" : 188,
    "value" : 0.5
  }, {
    "source" : 2,
    "target" : 189,
    "value" : 0.5
  }, {
    "source" : 2,
    "target" : 190,
    "value" : 0.5
  }, {
    "source" : 2,
    "target" : 191,
    "value" : 0.5
  }, {
    "source" : 2,
    "target" : 192,
    "value" : 0.5
  }, {
    "source" : 2,
    "target" : 52,
    "value" : 0.4
  }, {
    "source" : 2,
    "target" : 193,
    "value" : 0.333
  }, {
    "source" : 2,
    "target" : 194,
    "value" : 0.333
  }, {
    "source" : 2,
    "target" : 195,
    "value" : 0.333
  }, {
    "source" : 2,
    "target" : 196,
    "value" : 0.25
  }, {
    "source" : 2,
    "target" : 197,
    "value" : 0.2
  }, {
    "source" : 2,
    "target" : 77,
    "value" : 0.2
  }, {
    "source" : 2,
    "target" : 198,
    "value" : 0.2
  }, {
    "source" : 2,
    "target" : 198,
    "value" : 0.2
  }, {
    "source" : 2,
    "target" : 198,
    "value" : 0.2
  }, {
    "source" : 2,
    "target" : 199,
    "value" : 0.167
  }, {
    "source" : 2,
    "target" : 200,
    "value" : 0.1
  }, {
    "source" : 2,
    "target" : 9,
    "value" : 0.043
  }, {
    "source" : 2,
    "target" : 201,
    "value" : 0.043
  }, {
    "source" : 2,
    "target" : 1,
    "value" : 0.016
  }, {
    "source" : 2,
    "target" : 1,
    "value" : 0.013
  }, {
    "source" : 2,
    "target" : 1,
    "value" : 0.013
  }, {
    "source" : 2,
    "target" : 52,
    "value" : 0.011
  }, {
    "source" : 2,
    "target" : 202,
    "value" : 0.011
  }, {
    "source" : 2,
    "target" : 202,
    "value" : 0.011
  }, {
    "source" : 2,
    "target" : 3,
    "value" : 0.007
  }, {
    "source" : 2,
    "target" : 203,
    "value" : 0.005
  }, {
    "source" : 2,
    "target" : 204,
    "value" : 0.005
  }, {
    "source" : 2,
    "target" : 205,
    "value" : 0.005
  }, {
    "source" : 2,
    "target" : 206,
    "value" : 0.005
  }, {
    "source" : 2,
    "target" : 207,
    "value" : 0.005
  }, {
    "source" : 2,
    "target" : 208,
    "value" : 0.005
  }, {
    "source" : 2,
    "target" : 209,
    "value" : 0.005
  }, {
    "source" : 2,
    "target" : 210,
    "value" : 0.005
  }, {
    "source" : 2,
    "target" : 211,
    "value" : 0.005
  }, {
    "source" : 2,
    "target" : 212,
    "value" : 0.005
  }, {
    "source" : 2,
    "target" : 213,
    "value" : 0.005
  }, {
    "source" : 2,
    "target" : 214,
    "value" : 0.005
  }, {
    "source" : 2,
    "target" : 215,
    "value" : 0.005
  }, {
    "source" : 2,
    "target" : 216,
    "value" : 0.005
  }, {
    "source" : 2,
    "target" : 217,
    "value" : 0.005
  }, {
    "source" : 2,
    "target" : 218,
    "value" : 0.005
  }, {
    "source" : 2,
    "target" : 219,
    "value" : 0.005
  }, {
    "source" : 2,
    "target" : 220,
    "value" : 0.005
  }, {
    "source" : 2,
    "target" : 221,
    "value" : 0.005
  }, {
    "source" : 2,
    "target" : 222,
    "value" : 0.005
  }, {
    "source" : 2,
    "target" : 223,
    "value" : 0.005
  }, {
    "source" : 2,
    "target" : 224,
    "value" : 0.005
  }, {
    "source" : 2,
    "target" : 225,
    "value" : 0.005
  }, {
    "source" : 2,
    "target" : 226,
    "value" : 0.005
  }, {
    "source" : 2,
    "target" : 227,
    "value" : 0.005
  }, {
    "source" : 2,
    "target" : 228,
    "value" : 0.005
  }, {
    "source" : 2,
    "target" : 229,
    "value" : 0.005
  }, {
    "source" : 2,
    "target" : 230,
    "value" : 0.005
  }, {
    "source" : 2,
    "target" : 231,
    "value" : 0.005
  }, {
    "source" : 2,
    "target" : 232,
    "value" : 0.005
  }, {
    "source" : 2,
    "target" : 49,
    "value" : 0.005
  }, {
    "source" : 2,
    "target" : 7,
    "value" : 0.005
  }, {
    "source" : 2,
    "target" : 233,
    "value" : 0.005
  }, {
    "source" : 2,
    "target" : 234,
    "value" : 0.005
  }, {
    "source" : 2,
    "target" : 235,
    "value" : 0.005
  }, {
    "source" : 2,
    "target" : 236,
    "value" : 0.005
  }, {
    "source" : 2,
    "target" : 237,
    "value" : 0.005
  }, {
    "source" : 2,
    "target" : 238,
    "value" : 0.005
  }, {
    "source" : 2,
    "target" : 239,
    "value" : 0.005
  }, {
    "source" : 2,
    "target" : 240,
    "value" : 0.005
  }, {
    "source" : 2,
    "target" : 241,
    "value" : 0.0
  }, {
    "source" : 2,
    "target" : 242,
    "value" : 0.0
  }, {
    "source" : 2,
    "target" : 243,
    "value" : 0.0
  }, {
    "source" : 2,
    "target" : 64,
    "value" : 0.0
  }, {
    "source" : 2,
    "target" : 244,
    "value" : 0.0
  }, {
    "source" : 2,
    "target" : 245,
    "value" : 0.0
  }, {
    "source" : 2,
    "target" : 246,
    "value" : 0.0
  }, {
    "source" : 2,
    "target" : 247,
    "value" : 0.0
  }, {
    "source" : 2,
    "target" : 248,
    "value" : 0.0
  }, {
    "source" : 2,
    "target" : 249,
    "value" : 0.0
  }, {
    "source" : 2,
    "target" : 250,
    "value" : 0.0
  }, {
    "source" : 2,
    "target" : 251,
    "value" : 0.0
  }, {
    "source" : 2,
    "target" : 252,
    "value" : 0.0
  }, {
    "source" : 2,
    "target" : 253,
    "value" : 0.0
  }, {
    "source" : 2,
    "target" : 254,
    "value" : 0.0
  }, {
    "source" : 2,
    "target" : 255,
    "value" : 0.0
  }, {
    "source" : 2,
    "target" : 256,
    "value" : 0.0
  }, {
    "source" : 2,
    "target" : 257,
    "value" : 0.0
  }, {
    "source" : 2,
    "target" : 258,
    "value" : 0.0
  }, {
    "source" : 2,
    "target" : 259,
    "value" : 0.0
  }, {
    "source" : 2,
    "target" : 260,
    "value" : 0.0
  }, {
    "source" : 2,
    "target" : 261,
    "value" : 0.0
  }, {
    "source" : 2,
    "target" : 262,
    "value" : 0.0
  }, {
    "source" : 2,
    "target" : 263,
    "value" : 0.0
  }, {
    "source" : 2,
    "target" : 264,
    "value" : 0.0
  }, {
    "source" : 2,
    "target" : 111,
    "value" : 0.0
  }, {
    "source" : 2,
    "target" : 265,
    "value" : 0.0
  }, {
    "source" : 2,
    "target" : 266,
    "value" : 0.0
  }, {
    "source" : 2,
    "target" : 267,
    "value" : 0.0
  }, {
    "source" : 2,
    "target" : 268,
    "value" : 0.0
  }, {
    "source" : 2,
    "target" : 269,
    "value" : 0.0
  }, {
    "source" : 2,
    "target" : 270,
    "value" : 0.0
  }, {
    "source" : 2,
    "target" : 271,
    "value" : 0.0
  }, {
    "source" : 2,
    "target" : 272,
    "value" : 0.0
  }, {
    "source" : 2,
    "target" : 273,
    "value" : 0.0
  }, {
    "source" : 2,
    "target" : 274,
    "value" : 0.0
  }, {
    "source" : 2,
    "target" : 275,
    "value" : 0.0
  }, {
    "source" : 2,
    "target" : 276,
    "value" : 0.0
  }, {
    "source" : 2,
    "target" : 277,
    "value" : 0.0
  }, {
    "source" : 2,
    "target" : 278,
    "value" : 0.0
  }, {
    "source" : 2,
    "target" : 279,
    "value" : 0.0
  }, {
    "source" : 2,
    "target" : 280,
    "value" : 0.0
  }, {
    "source" : 2,
    "target" : 281,
    "value" : 0.0
  }, {
    "source" : 2,
    "target" : 282,
    "value" : 0.0
  }, {
    "source" : 2,
    "target" : 283,
    "value" : 0.0
  }, {
    "source" : 2,
    "target" : 284,
    "value" : 0.0
  }, {
    "source" : 2,
    "target" : 285,
    "value" : 0.0
  }, {
    "source" : 2,
    "target" : 286,
    "value" : 0.0
  }, {
    "source" : 2,
    "target" : 287,
    "value" : 0.0
  }, {
    "source" : 2,
    "target" : 288,
    "value" : 0.0
  }, {
    "source" : 2,
    "target" : 289,
    "value" : 0.0
  }, {
    "source" : 2,
    "target" : 290,
    "value" : 0.0
  }, {
    "source" : 2,
    "target" : 290,
    "value" : 0.0
  }, {
    "source" : 2,
    "target" : 291,
    "value" : 0.0
  }, {
    "source" : 2,
    "target" : 292,
    "value" : 0.0
  }, {
    "source" : 2,
    "target" : 293,
    "value" : 0.0
  }, {
    "source" : 2,
    "target" : 294,
    "value" : 0.0
  }, {
    "source" : 2,
    "target" : 295,
    "value" : 0.0
  }, {
    "source" : 2,
    "target" : 296,
    "value" : 0.0
  }, {
    "source" : 2,
    "target" : 297,
    "value" : 0.0
  }, {
    "source" : 2,
    "target" : 298,
    "value" : 0.0
  }, {
    "source" : 2,
    "target" : 299,
    "value" : 0.0
  }, {
    "source" : 2,
    "target" : 300,
    "value" : 0.0
  }, {
    "source" : 2,
    "target" : 301,
    "value" : 0.0
  }, {
    "source" : 2,
    "target" : 302,
    "value" : 0.0
  }, {
    "source" : 2,
    "target" : 303,
    "value" : 0.0
  }, {
    "source" : 2,
    "target" : 304,
    "value" : 0.0
  }, {
    "source" : 2,
    "target" : 305,
    "value" : 0.0
  }, {
    "source" : 2,
    "target" : 306,
    "value" : 0.0
  }, {
    "source" : 2,
    "target" : 307,
    "value" : 0.0
  }, {
    "source" : 2,
    "target" : 308,
    "value" : 0.0
  }, {
    "source" : 2,
    "target" : 309,
    "value" : 0.0
  }, {
    "source" : 2,
    "target" : 140,
    "value" : 0.0
  }, {
    "source" : 2,
    "target" : 310,
    "value" : 0.0
  }, {
    "source" : 2,
    "target" : 311,
    "value" : 0.0
  }, {
    "source" : 2,
    "target" : 312,
    "value" : 0.0
  }, {
    "source" : 2,
    "target" : 313,
    "value" : 0.0
  }, {
    "source" : 2,
    "target" : 313,
    "value" : 0.0
  }, {
    "source" : 2,
    "target" : 314,
    "value" : 0.0
  }, {
    "source" : 2,
    "target" : 315,
    "value" : 0.0
  }, {
    "source" : 2,
    "target" : 316,
    "value" : 0.0
  }, {
    "source" : 2,
    "target" : 317,
    "value" : 0.0
  }, {
    "source" : 2,
    "target" : 318,
    "value" : 0.0
  }, {
    "source" : 2,
    "target" : 319,
    "value" : 0.0
  }, {
    "source" : 2,
    "target" : 320,
    "value" : 0.0
  }, {
    "source" : 2,
    "target" : 321,
    "value" : 0.0
  }, {
    "source" : 2,
    "target" : 322,
    "value" : 0.0
  }, {
    "source" : 2,
    "target" : 177,
    "value" : 0.0
  }, {
    "source" : 2,
    "target" : 323,
    "value" : 0.0
  }, {
    "source" : 2,
    "target" : 324,
    "value" : 0.0
  }, {
    "source" : 2,
    "target" : 325,
    "value" : 0.0
  }, {
    "source" : 3,
    "target" : 326,
    "value" : 0.5
  }, {
    "source" : 3,
    "target" : 327,
    "value" : 0.5
  }, {
    "source" : 3,
    "target" : 328,
    "value" : 0.5
  }, {
    "source" : 3,
    "target" : 329,
    "value" : 0.5
  }, {
    "source" : 3,
    "target" : 330,
    "value" : 0.5
  }, {
    "source" : 3,
    "target" : 331,
    "value" : 0.5
  }, {
    "source" : 3,
    "target" : 332,
    "value" : 0.5
  }, {
    "source" : 3,
    "target" : 228,
    "value" : 0.5
  }, {
    "source" : 3,
    "target" : 333,
    "value" : 0.333
  }, {
    "source" : 3,
    "target" : 334,
    "value" : 0.333
  }, {
    "source" : 3,
    "target" : 335,
    "value" : 0.333
  }, {
    "source" : 3,
    "target" : 336,
    "value" : 0.25
  }, {
    "source" : 3,
    "target" : 337,
    "value" : 0.2
  }, {
    "source" : 3,
    "target" : 338,
    "value" : 0.083
  }, {
    "source" : 3,
    "target" : 198,
    "value" : 0.067
  }, {
    "source" : 3,
    "target" : 339,
    "value" : 0.026
  }, {
    "source" : 3,
    "target" : 340,
    "value" : 0.02
  }, {
    "source" : 3,
    "target" : 340,
    "value" : 0.02
  }, {
    "source" : 3,
    "target" : 340,
    "value" : 0.02
  }, {
    "source" : 3,
    "target" : 4,
    "value" : 0.017
  }, {
    "source" : 3,
    "target" : 341,
    "value" : 0.014
  }, {
    "source" : 3,
    "target" : 341,
    "value" : 0.014
  }, {
    "source" : 3,
    "target" : 342,
    "value" : 0.007
  }, {
    "source" : 3,
    "target" : 343,
    "value" : 0.007
  }, {
    "source" : 3,
    "target" : 344,
    "value" : 0.007
  }, {
    "source" : 3,
    "target" : 345,
    "value" : 0.007
  }, {
    "source" : 3,
    "target" : 346,
    "value" : 0.007
  }, {
    "source" : 3,
    "target" : 347,
    "value" : 0.007
  }, {
    "source" : 3,
    "target" : 348,
    "value" : 0.007
  }, {
    "source" : 3,
    "target" : 349,
    "value" : 0.007
  }, {
    "source" : 3,
    "target" : 350,
    "value" : 0.007
  }, {
    "source" : 3,
    "target" : 351,
    "value" : 0.007
  }, {
    "source" : 3,
    "target" : 2,
    "value" : 0.007
  }, {
    "source" : 3,
    "target" : 352,
    "value" : 0.007
  }, {
    "source" : 3,
    "target" : 353,
    "value" : 0.007
  }, {
    "source" : 3,
    "target" : 354,
    "value" : 0.007
  }, {
    "source" : 3,
    "target" : 355,
    "value" : 0.007
  }, {
    "source" : 3,
    "target" : 356,
    "value" : 0.007
  }, {
    "source" : 3,
    "target" : 53,
    "value" : 0.007
  }, {
    "source" : 3,
    "target" : 213,
    "value" : 0.007
  }, {
    "source" : 3,
    "target" : 357,
    "value" : 0.007
  }, {
    "source" : 3,
    "target" : 358,
    "value" : 0.007
  }, {
    "source" : 3,
    "target" : 359,
    "value" : 0.007
  }, {
    "source" : 3,
    "target" : 360,
    "value" : 0.007
  }, {
    "source" : 3,
    "target" : 361,
    "value" : 0.007
  }, {
    "source" : 3,
    "target" : 362,
    "value" : 0.007
  }, {
    "source" : 3,
    "target" : 363,
    "value" : 0.007
  }, {
    "source" : 3,
    "target" : 364,
    "value" : 0.007
  }, {
    "source" : 3,
    "target" : 365,
    "value" : 0.007
  }, {
    "source" : 3,
    "target" : 366,
    "value" : 0.007
  }, {
    "source" : 3,
    "target" : 367,
    "value" : 0.007
  }, {
    "source" : 3,
    "target" : 90,
    "value" : 0.007
  }, {
    "source" : 3,
    "target" : 368,
    "value" : 0.007
  }, {
    "source" : 3,
    "target" : 232,
    "value" : 0.007
  }, {
    "source" : 3,
    "target" : 369,
    "value" : 0.007
  }, {
    "source" : 3,
    "target" : 370,
    "value" : 0.007
  }, {
    "source" : 3,
    "target" : 7,
    "value" : 0.007
  }, {
    "source" : 3,
    "target" : 371,
    "value" : 0.007
  }, {
    "source" : 3,
    "target" : 372,
    "value" : 0.007
  }, {
    "source" : 3,
    "target" : 1,
    "value" : 0.004
  }, {
    "source" : 3,
    "target" : 373,
    "value" : 0.0
  }, {
    "source" : 3,
    "target" : 374,
    "value" : 0.0
  }, {
    "source" : 3,
    "target" : 375,
    "value" : 0.0
  }, {
    "source" : 3,
    "target" : 376,
    "value" : 0.0
  }, {
    "source" : 3,
    "target" : 377,
    "value" : 0.0
  }, {
    "source" : 3,
    "target" : 377,
    "value" : 0.0
  }, {
    "source" : 3,
    "target" : 378,
    "value" : 0.0
  }, {
    "source" : 3,
    "target" : 379,
    "value" : 0.0
  }, {
    "source" : 3,
    "target" : 380,
    "value" : 0.0
  }, {
    "source" : 3,
    "target" : 381,
    "value" : 0.0
  }, {
    "source" : 3,
    "target" : 382,
    "value" : 0.0
  }, {
    "source" : 3,
    "target" : 383,
    "value" : 0.0
  }, {
    "source" : 3,
    "target" : 384,
    "value" : 0.0
  }, {
    "source" : 3,
    "target" : 385,
    "value" : 0.0
  }, {
    "source" : 3,
    "target" : 386,
    "value" : 0.0
  }, {
    "source" : 3,
    "target" : 387,
    "value" : 0.0
  }, {
    "source" : 3,
    "target" : 388,
    "value" : 0.0
  }, {
    "source" : 3,
    "target" : 389,
    "value" : 0.0
  }, {
    "source" : 3,
    "target" : 116,
    "value" : 0.0
  }, {
    "source" : 3,
    "target" : 390,
    "value" : 0.0
  }, {
    "source" : 3,
    "target" : 391,
    "value" : 0.0
  }, {
    "source" : 3,
    "target" : 392,
    "value" : 0.0
  }, {
    "source" : 3,
    "target" : 393,
    "value" : 0.0
  }, {
    "source" : 3,
    "target" : 394,
    "value" : 0.0
  }, {
    "source" : 3,
    "target" : 395,
    "value" : 0.0
  }, {
    "source" : 3,
    "target" : 396,
    "value" : 0.0
  }, {
    "source" : 3,
    "target" : 397,
    "value" : 0.0
  }, {
    "source" : 3,
    "target" : 398,
    "value" : 0.0
  }, {
    "source" : 3,
    "target" : 399,
    "value" : 0.0
  }, {
    "source" : 3,
    "target" : 400,
    "value" : 0.0
  }, {
    "source" : 3,
    "target" : 401,
    "value" : 0.0
  }, {
    "source" : 3,
    "target" : 402,
    "value" : 0.0
  }, {
    "source" : 3,
    "target" : 403,
    "value" : 0.0
  }, {
    "source" : 3,
    "target" : 404,
    "value" : 0.0
  }, {
    "source" : 3,
    "target" : 405,
    "value" : 0.0
  }, {
    "source" : 3,
    "target" : 406,
    "value" : 0.0
  }, {
    "source" : 3,
    "target" : 407,
    "value" : 0.0
  }, {
    "source" : 3,
    "target" : 408,
    "value" : 0.0
  }, {
    "source" : 3,
    "target" : 409,
    "value" : 0.0
  }, {
    "source" : 3,
    "target" : 410,
    "value" : 0.0
  }, {
    "source" : 3,
    "target" : 411,
    "value" : 0.0
  }, {
    "source" : 3,
    "target" : 411,
    "value" : 0.0
  }, {
    "source" : 3,
    "target" : 412,
    "value" : 0.0
  }, {
    "source" : 3,
    "target" : 413,
    "value" : 0.0
  }, {
    "source" : 3,
    "target" : 414,
    "value" : 0.0
  }, {
    "source" : 3,
    "target" : 415,
    "value" : 0.0
  }, {
    "source" : 3,
    "target" : 416,
    "value" : 0.0
  }, {
    "source" : 3,
    "target" : 417,
    "value" : 0.0
  }, {
    "source" : 3,
    "target" : 296,
    "value" : 0.0
  }, {
    "source" : 3,
    "target" : 418,
    "value" : 0.0
  }, {
    "source" : 3,
    "target" : 419,
    "value" : 0.0
  }, {
    "source" : 3,
    "target" : 420,
    "value" : 0.0
  }, {
    "source" : 3,
    "target" : 421,
    "value" : 0.0
  }, {
    "source" : 3,
    "target" : 422,
    "value" : 0.0
  }, {
    "source" : 3,
    "target" : 423,
    "value" : 0.0
  }, {
    "source" : 3,
    "target" : 424,
    "value" : 0.0
  }, {
    "source" : 3,
    "target" : 425,
    "value" : 0.0
  }, {
    "source" : 3,
    "target" : 426,
    "value" : 0.0
  }, {
    "source" : 3,
    "target" : 427,
    "value" : 0.0
  }, {
    "source" : 3,
    "target" : 428,
    "value" : 0.0
  }, {
    "source" : 3,
    "target" : 429,
    "value" : 0.0
  }, {
    "source" : 3,
    "target" : 430,
    "value" : 0.0
  }, {
    "source" : 3,
    "target" : 431,
    "value" : 0.0
  }, {
    "source" : 3,
    "target" : 432,
    "value" : 0.0
  }, {
    "source" : 3,
    "target" : 433,
    "value" : 0.0
  }, {
    "source" : 3,
    "target" : 434,
    "value" : 0.0
  }, {
    "source" : 3,
    "target" : 435,
    "value" : 0.0
  }, {
    "source" : 3,
    "target" : 436,
    "value" : 0.0
  }, {
    "source" : 3,
    "target" : 177,
    "value" : 0.0
  }, {
    "source" : 3,
    "target" : 437,
    "value" : 0.0
  }, {
    "source" : 3,
    "target" : 438,
    "value" : 0.0
  }, {
    "source" : 4,
    "target" : 439,
    "value" : 0.5
  }, {
    "source" : 4,
    "target" : 440,
    "value" : 0.5
  }, {
    "source" : 4,
    "target" : 441,
    "value" : 0.5
  }, {
    "source" : 4,
    "target" : 442,
    "value" : 0.5
  }, {
    "source" : 4,
    "target" : 212,
    "value" : 0.5
  }, {
    "source" : 4,
    "target" : 443,
    "value" : 0.333
  }, {
    "source" : 4,
    "target" : 1,
    "value" : 0.333
  }, {
    "source" : 4,
    "target" : 444,
    "value" : 0.25
  }, {
    "source" : 4,
    "target" : 445,
    "value" : 0.167
  }, {
    "source" : 4,
    "target" : 446,
    "value" : 0.067
  }, {
    "source" : 4,
    "target" : 50,
    "value" : 0.042
  }, {
    "source" : 4,
    "target" : 5,
    "value" : 0.034
  }, {
    "source" : 4,
    "target" : 5,
    "value" : 0.033
  }, {
    "source" : 4,
    "target" : 447,
    "value" : 0.017
  }, {
    "source" : 4,
    "target" : 448,
    "value" : 0.017
  }, {
    "source" : 4,
    "target" : 449,
    "value" : 0.017
  }, {
    "source" : 4,
    "target" : 450,
    "value" : 0.017
  }, {
    "source" : 4,
    "target" : 451,
    "value" : 0.017
  }, {
    "source" : 4,
    "target" : 452,
    "value" : 0.017
  }, {
    "source" : 4,
    "target" : 3,
    "value" : 0.017
  }, {
    "source" : 4,
    "target" : 453,
    "value" : 0.017
  }, {
    "source" : 4,
    "target" : 454,
    "value" : 0.017
  }, {
    "source" : 4,
    "target" : 455,
    "value" : 0.017
  }, {
    "source" : 4,
    "target" : 247,
    "value" : 0.0
  }, {
    "source" : 4,
    "target" : 101,
    "value" : 0.0
  }, {
    "source" : 4,
    "target" : 456,
    "value" : 0.0
  }, {
    "source" : 4,
    "target" : 457,
    "value" : 0.0
  }, {
    "source" : 4,
    "target" : 457,
    "value" : 0.0
  }, {
    "source" : 4,
    "target" : 458,
    "value" : 0.0
  }, {
    "source" : 4,
    "target" : 459,
    "value" : 0.0
  }, {
    "source" : 4,
    "target" : 460,
    "value" : 0.0
  }, {
    "source" : 4,
    "target" : 461,
    "value" : 0.0
  }, {
    "source" : 4,
    "target" : 462,
    "value" : 0.0
  }, {
    "source" : 4,
    "target" : 463,
    "value" : 0.0
  }, {
    "source" : 4,
    "target" : 464,
    "value" : 0.0
  }, {
    "source" : 4,
    "target" : 465,
    "value" : 0.0
  }, {
    "source" : 4,
    "target" : 466,
    "value" : 0.0
  }, {
    "source" : 4,
    "target" : 467,
    "value" : 0.0
  }, {
    "source" : 4,
    "target" : 467,
    "value" : 0.0
  }, {
    "source" : 4,
    "target" : 467,
    "value" : 0.0
  }, {
    "source" : 4,
    "target" : 468,
    "value" : 0.0
  }, {
    "source" : 4,
    "target" : 469,
    "value" : 0.0
  }, {
    "source" : 4,
    "target" : 470,
    "value" : 0.0
  }, {
    "source" : 4,
    "target" : 471,
    "value" : 0.0
  }, {
    "source" : 4,
    "target" : 472,
    "value" : 0.0
  }, {
    "source" : 4,
    "target" : 473,
    "value" : 0.0
  }, {
    "source" : 4,
    "target" : 474,
    "value" : 0.0
  }, {
    "source" : 4,
    "target" : 475,
    "value" : 0.0
  }, {
    "source" : 4,
    "target" : 476,
    "value" : 0.0
  }, {
    "source" : 4,
    "target" : 477,
    "value" : 0.0
  }, {
    "source" : 4,
    "target" : 478,
    "value" : 0.0
  }, {
    "source" : 4,
    "target" : 479,
    "value" : 0.0
  }, {
    "source" : 4,
    "target" : 480,
    "value" : 0.0
  }, {
    "source" : 5,
    "target" : 450,
    "value" : 0.5
  }, {
    "source" : 5,
    "target" : 450,
    "value" : 0.5
  }, {
    "source" : 5,
    "target" : 481,
    "value" : 0.5
  }, {
    "source" : 5,
    "target" : 482,
    "value" : 0.5
  }, {
    "source" : 5,
    "target" : 483,
    "value" : 0.5
  }, {
    "source" : 5,
    "target" : 484,
    "value" : 0.5
  }, {
    "source" : 5,
    "target" : 485,
    "value" : 0.5
  }, {
    "source" : 5,
    "target" : 486,
    "value" : 0.5
  }, {
    "source" : 5,
    "target" : 487,
    "value" : 0.5
  }, {
    "source" : 5,
    "target" : 488,
    "value" : 0.5
  }, {
    "source" : 5,
    "target" : 489,
    "value" : 0.5
  }, {
    "source" : 5,
    "target" : 490,
    "value" : 0.5
  }, {
    "source" : 5,
    "target" : 491,
    "value" : 0.5
  }, {
    "source" : 5,
    "target" : 492,
    "value" : 0.5
  }, {
    "source" : 5,
    "target" : 493,
    "value" : 0.5
  }, {
    "source" : 5,
    "target" : 494,
    "value" : 0.333
  }, {
    "source" : 5,
    "target" : 448,
    "value" : 0.333
  }, {
    "source" : 5,
    "target" : 495,
    "value" : 0.333
  }, {
    "source" : 5,
    "target" : 496,
    "value" : 0.333
  }, {
    "source" : 5,
    "target" : 497,
    "value" : 0.333
  }, {
    "source" : 5,
    "target" : 498,
    "value" : 0.25
  }, {
    "source" : 5,
    "target" : 499,
    "value" : 0.25
  }, {
    "source" : 5,
    "target" : 500,
    "value" : 0.25
  }, {
    "source" : 5,
    "target" : 501,
    "value" : 0.2
  }, {
    "source" : 5,
    "target" : 502,
    "value" : 0.111
  }, {
    "source" : 5,
    "target" : 43,
    "value" : 0.111
  }, {
    "source" : 5,
    "target" : 503,
    "value" : 0.083
  }, {
    "source" : 5,
    "target" : 4,
    "value" : 0.034
  }, {
    "source" : 5,
    "target" : 455,
    "value" : 0.033
  }, {
    "source" : 5,
    "target" : 4,
    "value" : 0.033
  }, {
    "source" : 5,
    "target" : 504,
    "value" : 0.03
  }, {
    "source" : 5,
    "target" : 68,
    "value" : 0.028
  }, {
    "source" : 5,
    "target" : 8,
    "value" : 0.019
  }, {
    "source" : 5,
    "target" : 505,
    "value" : 0.017
  }, {
    "source" : 5,
    "target" : 506,
    "value" : 0.0
  }, {
    "source" : 5,
    "target" : 507,
    "value" : 0.0
  }, {
    "source" : 5,
    "target" : 459,
    "value" : 0.0
  }, {
    "source" : 5,
    "target" : 508,
    "value" : 0.0
  }, {
    "source" : 5,
    "target" : 509,
    "value" : 0.0
  }, {
    "source" : 5,
    "target" : 510,
    "value" : 0.0
  }, {
    "source" : 5,
    "target" : 511,
    "value" : 0.0
  }, {
    "source" : 5,
    "target" : 512,
    "value" : 0.0
  }, {
    "source" : 5,
    "target" : 513,
    "value" : 0.0
  }, {
    "source" : 5,
    "target" : 514,
    "value" : 0.0
  }, {
    "source" : 5,
    "target" : 515,
    "value" : 0.0
  }, {
    "source" : 5,
    "target" : 516,
    "value" : 0.0
  }, {
    "source" : 5,
    "target" : 517,
    "value" : 0.0
  }, {
    "source" : 5,
    "target" : 518,
    "value" : 0.0
  }, {
    "source" : 5,
    "target" : 519,
    "value" : 0.0
  }, {
    "source" : 5,
    "target" : 520,
    "value" : 0.0
  }, {
    "source" : 5,
    "target" : 521,
    "value" : 0.0
  }, {
    "source" : 5,
    "target" : 522,
    "value" : 0.0
  }, {
    "source" : 5,
    "target" : 523,
    "value" : 0.0
  }, {
    "source" : 5,
    "target" : 524,
    "value" : 0.0
  }, {
    "source" : 5,
    "target" : 525,
    "value" : 0.0
  }, {
    "source" : 5,
    "target" : 526,
    "value" : 0.0
  }, {
    "source" : 5,
    "target" : 527,
    "value" : 0.0
  }, {
    "source" : 5,
    "target" : 528,
    "value" : 0.0
  }, {
    "source" : 5,
    "target" : 528,
    "value" : 0.0
  }, {
    "source" : 6,
    "target" : 20,
    "value" : 0.5
  }, {
    "source" : 6,
    "target" : 83,
    "value" : 0.5
  }, {
    "source" : 6,
    "target" : 529,
    "value" : 0.5
  }, {
    "source" : 6,
    "target" : 530,
    "value" : 0.333
  }, {
    "source" : 6,
    "target" : 1,
    "value" : 0.073
  }, {
    "source" : 6,
    "target" : 1,
    "value" : 0.073
  }, {
    "source" : 6,
    "target" : 531,
    "value" : 0.036
  }, {
    "source" : 6,
    "target" : 531,
    "value" : 0.036
  }, {
    "source" : 6,
    "target" : 58,
    "value" : 0.018
  }, {
    "source" : 6,
    "target" : 532,
    "value" : 0.018
  }, {
    "source" : 6,
    "target" : 533,
    "value" : 0.018
  }, {
    "source" : 6,
    "target" : 23,
    "value" : 0.018
  }, {
    "source" : 6,
    "target" : 534,
    "value" : 0.018
  }, {
    "source" : 6,
    "target" : 535,
    "value" : 0.018
  }, {
    "source" : 6,
    "target" : 536,
    "value" : 0.018
  }, {
    "source" : 6,
    "target" : 18,
    "value" : 0.018
  }, {
    "source" : 6,
    "target" : 53,
    "value" : 0.018
  }, {
    "source" : 6,
    "target" : 537,
    "value" : 0.018
  }, {
    "source" : 6,
    "target" : 481,
    "value" : 0.018
  }, {
    "source" : 6,
    "target" : 488,
    "value" : 0.018
  }, {
    "source" : 6,
    "target" : 538,
    "value" : 0.018
  }, {
    "source" : 6,
    "target" : 40,
    "value" : 0.018
  }, {
    "source" : 6,
    "target" : 539,
    "value" : 0.018
  }, {
    "source" : 6,
    "target" : 341,
    "value" : 0.018
  }, {
    "source" : 6,
    "target" : 1,
    "value" : 0.017
  }, {
    "source" : 6,
    "target" : 1,
    "value" : 0.017
  }, {
    "source" : 6,
    "target" : 540,
    "value" : 0.0
  }, {
    "source" : 6,
    "target" : 541,
    "value" : 0.0
  }, {
    "source" : 6,
    "target" : 542,
    "value" : 0.0
  }, {
    "source" : 6,
    "target" : 543,
    "value" : 0.0
  }, {
    "source" : 6,
    "target" : 544,
    "value" : 0.0
  }, {
    "source" : 6,
    "target" : 545,
    "value" : 0.0
  }, {
    "source" : 6,
    "target" : 546,
    "value" : 0.0
  }, {
    "source" : 6,
    "target" : 547,
    "value" : 0.0
  }, {
    "source" : 6,
    "target" : 397,
    "value" : 0.0
  }, {
    "source" : 6,
    "target" : 548,
    "value" : 0.0
  }, {
    "source" : 6,
    "target" : 549,
    "value" : 0.0
  }, {
    "source" : 6,
    "target" : 550,
    "value" : 0.0
  }, {
    "source" : 6,
    "target" : 551,
    "value" : 0.0
  }, {
    "source" : 6,
    "target" : 552,
    "value" : 0.0
  }, {
    "source" : 6,
    "target" : 553,
    "value" : 0.0
  }, {
    "source" : 6,
    "target" : 554,
    "value" : 0.0
  }, {
    "source" : 6,
    "target" : 555,
    "value" : 0.0
  }, {
    "source" : 6,
    "target" : 556,
    "value" : 0.0
  }, {
    "source" : 6,
    "target" : 557,
    "value" : 0.0
  }, {
    "source" : 6,
    "target" : 558,
    "value" : 0.0
  }, {
    "source" : 7,
    "target" : 559,
    "value" : 0.667
  }, {
    "source" : 7,
    "target" : 559,
    "value" : 0.667
  }, {
    "source" : 7,
    "target" : 204,
    "value" : 0.5
  }, {
    "source" : 7,
    "target" : 560,
    "value" : 0.5
  }, {
    "source" : 7,
    "target" : 561,
    "value" : 0.5
  }, {
    "source" : 7,
    "target" : 195,
    "value" : 0.333
  }, {
    "source" : 7,
    "target" : 562,
    "value" : 0.25
  }, {
    "source" : 7,
    "target" : 563,
    "value" : 0.2
  }, {
    "source" : 7,
    "target" : 564,
    "value" : 0.143
  }, {
    "source" : 7,
    "target" : 502,
    "value" : 0.111
  }, {
    "source" : 7,
    "target" : 565,
    "value" : 0.1
  }, {
    "source" : 7,
    "target" : 566,
    "value" : 0.018
  }, {
    "source" : 7,
    "target" : 567,
    "value" : 0.018
  }, {
    "source" : 7,
    "target" : 568,
    "value" : 0.018
  }, {
    "source" : 7,
    "target" : 569,
    "value" : 0.018
  }, {
    "source" : 7,
    "target" : 3,
    "value" : 0.007
  }, {
    "source" : 7,
    "target" : 2,
    "value" : 0.005
  }, {
    "source" : 7,
    "target" : 1,
    "value" : 0.004
  }, {
    "source" : 7,
    "target" : 570,
    "value" : 0.0
  }, {
    "source" : 7,
    "target" : 571,
    "value" : 0.0
  }, {
    "source" : 7,
    "target" : 572,
    "value" : 0.0
  }, {
    "source" : 7,
    "target" : 573,
    "value" : 0.0
  }, {
    "source" : 7,
    "target" : 574,
    "value" : 0.0
  }, {
    "source" : 7,
    "target" : 575,
    "value" : 0.0
  }, {
    "source" : 7,
    "target" : 576,
    "value" : 0.0
  }, {
    "source" : 7,
    "target" : 577,
    "value" : 0.0
  }, {
    "source" : 7,
    "target" : 578,
    "value" : 0.0
  }, {
    "source" : 7,
    "target" : 579,
    "value" : 0.0
  }, {
    "source" : 7,
    "target" : 580,
    "value" : 0.0
  }, {
    "source" : 7,
    "target" : 581,
    "value" : 0.0
  }, {
    "source" : 7,
    "target" : 582,
    "value" : 0.0
  }, {
    "source" : 7,
    "target" : 583,
    "value" : 0.0
  }, {
    "source" : 7,
    "target" : 584,
    "value" : 0.0
  }, {
    "source" : 7,
    "target" : 585,
    "value" : 0.0
  }, {
    "source" : 7,
    "target" : 586,
    "value" : 0.0
  }, {
    "source" : 7,
    "target" : 587,
    "value" : 0.0
  }, {
    "source" : 7,
    "target" : 588,
    "value" : 0.0
  }, {
    "source" : 7,
    "target" : 589,
    "value" : 0.0
  }, {
    "source" : 7,
    "target" : 590,
    "value" : 0.0
  }, {
    "source" : 7,
    "target" : 591,
    "value" : 0.0
  }, {
    "source" : 7,
    "target" : 591,
    "value" : 0.0
  }, {
    "source" : 7,
    "target" : 1,
    "value" : 0.0
  }, {
    "source" : 7,
    "target" : 592,
    "value" : 0.0
  }, {
    "source" : 7,
    "target" : 593,
    "value" : 0.0
  }, {
    "source" : 7,
    "target" : 594,
    "value" : 0.0
  }, {
    "source" : 7,
    "target" : 595,
    "value" : 0.0
  }, {
    "source" : 7,
    "target" : 596,
    "value" : 0.0
  }, {
    "source" : 7,
    "target" : 597,
    "value" : 0.0
  }, {
    "source" : 8,
    "target" : 598,
    "value" : 0.5
  }, {
    "source" : 8,
    "target" : 599,
    "value" : 0.5
  }, {
    "source" : 8,
    "target" : 209,
    "value" : 0.5
  }, {
    "source" : 8,
    "target" : 600,
    "value" : 0.333
  }, {
    "source" : 8,
    "target" : 601,
    "value" : 0.333
  }, {
    "source" : 8,
    "target" : 215,
    "value" : 0.125
  }, {
    "source" : 8,
    "target" : 602,
    "value" : 0.1
  }, {
    "source" : 8,
    "target" : 446,
    "value" : 0.067
  }, {
    "source" : 8,
    "target" : 338,
    "value" : 0.038
  }, {
    "source" : 8,
    "target" : 603,
    "value" : 0.038
  }, {
    "source" : 8,
    "target" : 604,
    "value" : 0.038
  }, {
    "source" : 8,
    "target" : 343,
    "value" : 0.037
  }, {
    "source" : 8,
    "target" : 605,
    "value" : 0.019
  }, {
    "source" : 8,
    "target" : 5,
    "value" : 0.019
  }, {
    "source" : 8,
    "target" : 606,
    "value" : 0.019
  }, {
    "source" : 8,
    "target" : 607,
    "value" : 0.019
  }, {
    "source" : 8,
    "target" : 608,
    "value" : 0.019
  }, {
    "source" : 8,
    "target" : 609,
    "value" : 0.019
  }, {
    "source" : 8,
    "target" : 443,
    "value" : 0.019
  }, {
    "source" : 8,
    "target" : 499,
    "value" : 0.019
  }, {
    "source" : 8,
    "target" : 610,
    "value" : 0.019
  }, {
    "source" : 8,
    "target" : 501,
    "value" : 0.019
  }, {
    "source" : 8,
    "target" : 611,
    "value" : 0.019
  }, {
    "source" : 8,
    "target" : 612,
    "value" : 0.0
  }, {
    "source" : 8,
    "target" : 613,
    "value" : 0.0
  }, {
    "source" : 8,
    "target" : 614,
    "value" : 0.0
  }, {
    "source" : 8,
    "target" : 615,
    "value" : 0.0
  }, {
    "source" : 8,
    "target" : 616,
    "value" : 0.0
  }, {
    "source" : 8,
    "target" : 617,
    "value" : 0.0
  }, {
    "source" : 8,
    "target" : 618,
    "value" : 0.0
  }, {
    "source" : 8,
    "target" : 619,
    "value" : 0.0
  }, {
    "source" : 8,
    "target" : 620,
    "value" : 0.0
  }, {
    "source" : 8,
    "target" : 621,
    "value" : 0.0
  }, {
    "source" : 8,
    "target" : 622,
    "value" : 0.0
  }, {
    "source" : 8,
    "target" : 623,
    "value" : 0.0
  }, {
    "source" : 8,
    "target" : 624,
    "value" : 0.0
  }, {
    "source" : 8,
    "target" : 625,
    "value" : 0.0
  }, {
    "source" : 8,
    "target" : 626,
    "value" : 0.0
  }, {
    "source" : 8,
    "target" : 627,
    "value" : 0.0
  }, {
    "source" : 8,
    "target" : 313,
    "value" : 0.0
  }, {
    "source" : 8,
    "target" : 628,
    "value" : 0.0
  }, {
    "source" : 8,
    "target" : 629,
    "value" : 0.0
  }, {
    "source" : 8,
    "target" : 630,
    "value" : 0.0
  }, {
    "source" : 9,
    "target" : 631,
    "value" : 0.333
  }, {
    "source" : 9,
    "target" : 1,
    "value" : 0.13
  }, {
    "source" : 9,
    "target" : 1,
    "value" : 0.13
  }, {
    "source" : 9,
    "target" : 1,
    "value" : 0.13
  }, {
    "source" : 9,
    "target" : 1,
    "value" : 0.13
  }, {
    "source" : 9,
    "target" : 1,
    "value" : 0.13
  }, {
    "source" : 9,
    "target" : 1,
    "value" : 0.13
  }, {
    "source" : 9,
    "target" : 58,
    "value" : 0.111
  }, {
    "source" : 9,
    "target" : 2,
    "value" : 0.043
  }, {
    "source" : 9,
    "target" : 632,
    "value" : 0.022
  }, {
    "source" : 9,
    "target" : 633,
    "value" : 0.022
  }, {
    "source" : 9,
    "target" : 634,
    "value" : 0.022
  }, {
    "source" : 9,
    "target" : 635,
    "value" : 0.022
  }, {
    "source" : 9,
    "target" : 180,
    "value" : 0.022
  }, {
    "source" : 9,
    "target" : 636,
    "value" : 0.022
  }, {
    "source" : 9,
    "target" : 637,
    "value" : 0.022
  }, {
    "source" : 9,
    "target" : 87,
    "value" : 0.022
  }, {
    "source" : 9,
    "target" : 638,
    "value" : 0.0
  }, {
    "source" : 9,
    "target" : 639,
    "value" : 0.0
  }, {
    "source" : 9,
    "target" : 640,
    "value" : 0.0
  }, {
    "source" : 9,
    "target" : 641,
    "value" : 0.0
  }, {
    "source" : 9,
    "target" : 386,
    "value" : 0.0
  }, {
    "source" : 9,
    "target" : 642,
    "value" : 0.0
  }, {
    "source" : 9,
    "target" : 643,
    "value" : 0.0
  }, {
    "source" : 9,
    "target" : 644,
    "value" : 0.0
  }, {
    "source" : 9,
    "target" : 645,
    "value" : 0.0
  }, {
    "source" : 9,
    "target" : 646,
    "value" : 0.0
  }, {
    "source" : 9,
    "target" : 647,
    "value" : 0.0
  }, {
    "source" : 9,
    "target" : 648,
    "value" : 0.0
  }, {
    "source" : 9,
    "target" : 649,
    "value" : 0.0
  }, {
    "source" : 9,
    "target" : 650,
    "value" : 0.0
  }, {
    "source" : 9,
    "target" : 651,
    "value" : 0.0
  }, {
    "source" : 9,
    "target" : 138,
    "value" : 0.0
  }, {
    "source" : 9,
    "target" : 652,
    "value" : 0.0
  }, {
    "source" : 9,
    "target" : 653,
    "value" : 0.0
  }, {
    "source" : 10,
    "target" : 654,
    "value" : 0.5
  }, {
    "source" : 10,
    "target" : 566,
    "value" : 0.333
  }, {
    "source" : 10,
    "target" : 655,
    "value" : 0.333
  }, {
    "source" : 10,
    "target" : 656,
    "value" : 0.083
  }, {
    "source" : 10,
    "target" : 657,
    "value" : 0.025
  }, {
    "source" : 10,
    "target" : 658,
    "value" : 0.025
  }, {
    "source" : 10,
    "target" : 659,
    "value" : 0.025
  }, {
    "source" : 10,
    "target" : 485,
    "value" : 0.025
  }, {
    "source" : 10,
    "target" : 660,
    "value" : 0.025
  }, {
    "source" : 10,
    "target" : 604,
    "value" : 0.025
  }, {
    "source" : 10,
    "target" : 327,
    "value" : 0.025
  }, {
    "source" : 10,
    "target" : 531,
    "value" : 0.025
  }, {
    "source" : 10,
    "target" : 94,
    "value" : 0.025
  }, {
    "source" : 10,
    "target" : 661,
    "value" : 0.025
  }, {
    "source" : 10,
    "target" : 662,
    "value" : 0.0
  }, {
    "source" : 10,
    "target" : 663,
    "value" : 0.0
  }, {
    "source" : 10,
    "target" : 664,
    "value" : 0.0
  }, {
    "source" : 10,
    "target" : 665,
    "value" : 0.0
  }, {
    "source" : 10,
    "target" : 666,
    "value" : 0.0
  }, {
    "source" : 10,
    "target" : 667,
    "value" : 0.0
  }, {
    "source" : 10,
    "target" : 668,
    "value" : 0.0
  }, {
    "source" : 10,
    "target" : 574,
    "value" : 0.0
  }, {
    "source" : 10,
    "target" : 669,
    "value" : 0.0
  }, {
    "source" : 10,
    "target" : 670,
    "value" : 0.0
  }, {
    "source" : 10,
    "target" : 392,
    "value" : 0.0
  }, {
    "source" : 10,
    "target" : 671,
    "value" : 0.0
  }, {
    "source" : 10,
    "target" : 672,
    "value" : 0.0
  }, {
    "source" : 10,
    "target" : 673,
    "value" : 0.0
  }, {
    "source" : 10,
    "target" : 674,
    "value" : 0.0
  }, {
    "source" : 10,
    "target" : 675,
    "value" : 0.0
  }, {
    "source" : 10,
    "target" : 676,
    "value" : 0.0
  }, {
    "source" : 10,
    "target" : 677,
    "value" : 0.0
  }, {
    "source" : 10,
    "target" : 295,
    "value" : 0.0
  }, {
    "source" : 10,
    "target" : 678,
    "value" : 0.0
  }, {
    "source" : 10,
    "target" : 595,
    "value" : 0.0
  }, {
    "source" : 10,
    "target" : 679,
    "value" : 0.0
  }, {
    "source" : 10,
    "target" : 680,
    "value" : 0.0
  }, {
    "source" : 10,
    "target" : 681,
    "value" : 0.0
  } ]
}
